Workbook

Sheet README
A1: Custom packaging startup, Kathmandu Valley - financial model (NPR). Research cut-off: 2026-10-23.
A2: Colour code: BLUE font = input/assumption; black = formula. Every input is an ASSUMPTION unless the Source column says otherwise.
A3: IMPORTANT: no supplier quotation was obtained in this research. Supplier costs, selling prices, AOV, conversion and reorder rates are budgetary assumptions (confidence LOW) to be replaced with RFQ results (see 06_supplier_quotation_request.md).
A4: v2 (audit): VAT-input toggle, mix-weighted AOV/margin, founder design time no longer double-counted. See 13_audit_report.md.
A5: Engine sheet holds 12 monthly engines (3 scenarios + 9 stress tests). P&L, Cash_Flow, Working_Capital show the Base engine.
A6: Checks sheet confirms the recommended budget reconciles to NPR 5,00,000.

Sheet Assumptions
A1: Parameter | B1: Value | C1: Unit | D1: Source / confidence
A2: Initial investment ceiling | B2: 500000 | C2: NPR | D2: Founder constraint (brief). High
A3: NPR per 100 INR (selling) | B3: 160.15 | C3: NPR/100 INR | D3: NRB forex, 12 Oct 2026 via sharesansar.com. High (may have moved)
A4: NPR per 1 USD (selling) | B4: 155.08 | C4: NPR/USD | D4: NRB forex, 12 Oct 2026 via sharesansar.com. High (may have moved)
A5: Average order value (blended, ex-VAT) | B5: =SUMPRODUCT(Product_Pricing!$S$2:$S$31,Product_Pricing!$T$2:$T$31,Product_Pricing!$K$2:$K$31)/SUMPRODUCT(Product_Pricing!$S$2:$S$31,Product_Pricing!$T$2:$T$31) -> 26718.75 | C5: NPR | D5: FORMULA (v2): order-mix-weighted average order value at each product's minimum-viable (MOQ) tier (v1 used a simple average that over-weighted rigid boxes); underlying prices are assumptions. Low
A6: Gross margin used by engine (mix-weighted, MOQ tiers) | B6: =IF(Assumptions!$B$28=1,SUMPRODUCT(Product_Pricing!$S$2:$S$31,Product_Pricing!$T$2:$T$31,Product_Pricing!$M$2:$M$31),SUMPRODUCT(Product_Pricing!$S$2:$S$31,Product_Pricing!$T$2:$T$31,Product_Pricing!$M$2:$M$31)+SUMPRODUCT(Product_Pricing!$S$2:$S$31,Product_Pricing!$T$2:$T$31,Product_Pricing!$E$2:$E$31))/SUMPRODUCT(Product_Pricing!$S$2:$S$31,Product_Pricing!$T$2:$T$31,Product_Pricing!$K$2:$K$31) -> 0.31611696 | C6: ratio | D6: FORMULA (v2): revenue- and mix-weighted gross margin at MOQ tiers; excludes founder design time unless design_cash=1. Low
A7: Delivery, payment-fee & selling variable cost | B7: 0.04 | C7: % revenue | D7: ASSUMPTION. Low
A8: Rework / rejection allowance | B8: 0.02 | C8: % revenue | D8: ASSUMPTION. Low
A9: Customer deposit at order | B9: 0.5 | C9: ratio | D9: Policy recommended in this study. Medium
A10: Credit days on balance | B10: 30 | C10: days | D10: ASSUMPTION; Kathmandu SME norm unverified. Low
A11: Monthly reorder probability per existing customer | B11: 0.18 | C11: ratio/month | D11: ASSUMPTION - conservative (reorder every ~5-6 months). Low
A12: Founder compensation (once started) | B12: 15000 | C12: NPR/month | D12: ASSUMPTION - shown explicitly so profit is not overstated
A13: Founder pay starts in month | B13: 7 | C13: month | D13: ASSUMPTION
A14: Rent (shared desk / small room) | B14: 8000 | C14: NPR/month | D14: ASSUMPTION - verify listings. Low
A15: Electricity & internet | B15: 3000 | C15: NPR/month | D15: ASSUMPTION. Low
A16: Software subscriptions | B16: 2000 | C16: NPR/month | D16: ASSUMPTION. Low
A17: Marketing (ads, samples, boosts) | B17: 10000 | C17: NPR/month | D17: ASSUMPTION. Low
A18: Transport & local delivery | B18: 3500 | C18: NPR/month | D18: ASSUMPTION. Low
... A28: Treat founder design time as a cash cost? (1 = yes) | B28: 0 | C28: flag | D28: AUDIT FIX v2: v1 deducted design labour as cash AND later paid founder salary (double count). 0 = design time is covered by founder pay
A29: Total fixed opex (excl. founder) | B29: =SUM(B14:B20) -> 32500 | C29: NPR/month
A31: New customers per month - base (funnel: ~60 contacts/mo x ~10% qualify x ~30-40% order)
A32: Month | B32: 1 | C32: 2 | D32: 3 | E32: 4 | F32: 5 | G32: 6 | H32: 7 | I32: 8 | J32: 9 | K32: 10 | L32: 11 | M32: 12
A33: New paying customers | B33: 0 | C33: 1 | D33: 2 | E33: 3 | F33: 3 | G33: 4 | H33: 4 | I33: 5 | J33: 5 | K33: 5 | L33: 6 | M33: 6
A34: Source: ASSUMPTION; to be replaced by measured funnel from 90-day pilot. Low

Sheet Scenario_Inputs
A1: Scenario | B1: Price x | C1: Supplier cost x | D1: New-customer x | E1: Repeat x | F1: Extra collection days | G1: M1 | H1: M2 | I1: M3 | J1: M4 | K1: M5 | L1: M6 | M1: M7 | N1: M8 | O1: M9 | P1: M10 | Q1: M11 | R1: M12
A2: (Row 1 of each scenario: multipliers. Row 2: monthly revenue multiplier. Row 3: monthly one-off cost NPR)
A3: Downside | B3: 1 | C3: 1.1 | D3: 0.5 | E3: 0.6 | F3: 30
A4: revenue multiplier by month | G4: 1 | H4: 1 | I4: 1 | J4: 1 | K4: 1 | L4: 1 | M4: 1 | N4: 1 | O4: 1 | P4: 1 | Q4: 1 | R4: 1
A5: one-off cost by month (NPR) | G5: 0 | H5: 0 | I5: 0 | J5: 0 | K5: 0 | L5: 0 | M5: 0 | N5: 0 | O5: 0 | P5: 0 | Q5: 0 | R5: 0
A7: Base | B7: 1 | C7: 1 | D7: 1 | E7: 1 | F7: 0
A8: revenue multiplier by month | G8: 1 | H8: 1 | I8: 1 | J8: 1 | K8: 1 | L8: 1 | M8: 1 | N8: 1 | O8: 1 | P8: 1 | Q8: 1 | R8: 1
A9: one-off cost by month (NPR) | G9: 0 | H9: 0 | I9: 0 | J9: 0 | K9: 0 | L9: 0 | M9: 0 | N9: 0 | O9: 0 | P9: 0 | Q9: 0 | R9: 0
A11: Upside | B11: 1 | C11: 0.97 | D11: 1.4 | E11: 1.3 | F11: 0
A12: revenue multiplier by month | G12: 1 | H12: 1 | I12: 1 | J12: 1 | K12: 1 | L12: 1 | M12: 1 | N12: 1 | O12: 1 | P12: 1 | Q12: 1 | R12: 1
A13: one-off cost by month (NPR) | G13: 0 | H13: 0 | I13: 0 | J13: 0 | K13: 0 | L13: 0 | M13: 0 | N13: 0 | O13: 0 | P13: 0 | Q13: 0 | R13: 0
A15: S1 Selling prices -10% | B15: 0.9 | C15: 1 | D15: 1 | E15: 1 | F15: 0
A16: revenue multiplier by month | G16: 1 | H16: 1 | I16: 1 | J16: 1 | K16: 1 | L16: 1 | M16: 1 | N16: 1 | O16: 1 | P16: 1 | Q16: 1 | R16: 1
A17: one-off cost by month (NPR) | G17: 0 | H17: 0 | I17: 0 | J17: 0 | K17: 0 | L17: 0 | M17: 0 | N17: 0 | O17: 0 | P17: 0 | Q17: 0 | R17: 0
A19: S2 Outsourcing cost +10% | B19: 1 | C19: 1.1 | D19: 1 | E19: 1 | F19: 0
A20: revenue multiplier by month | G20: 1 | H20: 1 | I20: 1 | J20: 1 | K20: 1 | L20: 1 | M20: 1 | N20: 1 | O20: 1 | P20: 1 | Q20: 1 | R20: 1
A21: one-off cost by month (NPR) | G21: 0 | H21: 0 | I21: 0 | J21: 0 | K21: 0 | L21: 0 | M21: 0 | N21: 0 | O21: 0 | P21: 0 | Q21: 0 | R21: 0
A23: S3 Customer acquisition 50% slower | B23: 1 | C23: 1 | D23: 0.5 | E23: 1 | F23: 0
A24: revenue multiplier by month | G24: 1 | H24: 1 | I24: 1 | J24: 1 | K24: 1 | L24: 1 | M24: 1 | N24: 1 | O24: 1 | P24: 1 | Q24: 1 | R24: 1
A25: one-off cost by month (NPR) | G25: 0 | H25: 0 | I25: 0 | J25: 0 | K25: 0 | L25: 0 | M25: 0 | N25: 0 | O25: 0 | P25: 0 | Q25: 0 | R25: 0
A27: S4 Material cost +15% | B27: 1 | C27: 1.15 | D27: 1 | E27: 1 | F27: 0
A28: revenue multiplier by month | G28: 1 | H28: 1 | I28: 1 | J28: 1 | K28: 1 | L28: 1 | M28: 1 | N28: 1 | O28: 1 | P28: 1 | Q28: 1 | R28: 1
A29: one-off cost by month (NPR) | G29: 0 | H29: 0 | I29: 0 | J29: 0 | K29: 0 | L29: 0 | M29: 0 | N29: 0 | O29: 0 | P29: 0 | Q29: 0 | R29: 0
A31: S5 Customers pay 30 days later | B31: 1 | C31: 1 | D31: 1 | E31: 1 | F31: 30
A32: revenue multiplier by month | G32: 1 | H32: 1 | I32: 1 | J32: 1 | K32: 1 | L32: 1 | M32: 1 | N32: 1 | O32: 1 | P32: 1 | Q32: 1 | R32: 1
A33: one-off cost by month (NPR) | G33: 0 | H33: 0 | I33: 0 | J33: 0 | K33: 0 | L33: 0 | M33: 0 | N33: 0 | O33: 0 | P33: 0 | Q33: 0 | R33: 0
A35: S6 Key supplier fails (months 5-6 sales at 40%, 15k rework) | B35: 1 | C35: 1 | D35: 1 | E35: 1 | F35: 0
A36: revenue multiplier by month | G36: 1 | H36: 1 | I36: 1 | J36: 1 | K36: 0.4 | L36: 0.4 | M36: 1 | N36: 1 | O36: 1 | P36: 1 | Q36: 1 | R36: 1
A37: one-off cost by month (NPR) | G37: 0 | H37: 0 | I37: 0 | J37: 0 | K37: 15000 | L37: 0 | M37: 0 | N37: 0 | O37: 0 | P37: 0 | Q37: 0 | R37: 0
A39: S7 Repeat purchases 50% lower | B39: 1 | C39: 1 | D39: 1 | E39: 0.5 | F39: 0
A40: revenue multiplier by month | G40: 1 | H40: 1 | I40: 1 | J40: 1 | K40: 1 | L40: 1 | M40: 1 | N40: 1 | O40: 1 | P40: 1 | Q40: 1 | R40: 1
A41: one-off cost by month (NPR) | G41: 0 | H41: 0 | I41: 0 | J41: 0 | K41: 0 | L41: 0 | M41: 0 | N41: 0 | O41: 0 | P41: 0 | Q41: 0 | R41: 0
A43: S8 Seasonal concentration (M1-6 at 60%, M7-12 at 140%) | B43: 1 | C43: 1 | D43: 1 | E43: 1 | F43: 0
A44: revenue multiplier by month | G44: 0.6 | H44: 0.6 | I44: 0.6 | J44: 0.6 | K44: 0.6 | L44: 0.6 | M44: 1.4 | N44: 1.4 | O44: 1.4 | P44: 1.4 | Q44: 1.4 | R44: 1.4
A45: one-off cost by month (NPR) | G45: 0 | H45: 0 | I45: 0 | J45: 0 | K45: 0 | L45: 0 | M45: 0 | N45: 0 | O45: 0 | P45: 0 | Q45: 0 | R45: 0
A47: S9 Unusable output write-off 25k in M4 + tool repair 20k in M8 | B47: 1 | C47: 1 | D47: 1 | E47: 1 | F47: 0
A48: revenue multiplier by month | G48: 1 | H48: 1 | I48: 1 | J48: 1 | K48: 1 | L48: 1 | M48: 1 | N48: 1 | O48: 1 | P48: 1 | Q48: 1 | R48: 1
A49: one-off cost by month (NPR) | G49: 0 | H49: 0 | I49: 0 | J49: 25000 | K49: 0 | L49: 0 | M49: 0 | N49: 20000 | O49: 0 | P49: 0 | Q49: 0 | R49: 0

Sheet Capital_Allocation
A1: Item (NPR) | B1: Config A: validation | C1: Config B: RECOMMENDED | D1: Config B-own: founder owns laptop/space | E1: Config C: higher capability (needs more capital) | F1: Basis (all budgetary assumptions unless stated; low confidence)
A2: Refurbished design laptop | B2: 0 | C2: 55000 | D2: 0 | E2: 55000 | F2: Used/refurb laptop; Config A assumes founder's own
A3: Design software (12 months) | B3: 8000 | C3: 15000 | D3: 15000 | E3: 15000 | F3: Subscription estimate
A4: Hand tools & finishing kit (A3 guillotine, creasing, steel rule, mats) | B4: 10000 | C4: 30000 | D4: 30000 | E4: 30000 | F4: No powered conversion machinery in B
A5: Furniture & storage | B5: 0 | C5: 15000 | D5: 15000 | E5: 15000 | F5: Table, racks
A6: Premises deposit & basic fit-out | B6: 0 | C6: 25000 | D6: 0 | E6: 25000 | F6: ~2 months rent + fit-out
A7: Supplier samples & prototypes | B7: 25000 | C7: 40000 | D7: 40000 | E7: 40000 | F7: Sample budget across 6 product types and 3+ suppliers
A8: Initial materials / sample-kit stock | B8: 0 | C8: 20000 | D8: 20000 | E8: 20000 | F8: Sample kits for outreach
A9: Registration, CA & professional support | B9: 12000 | C9: 20000 | D9: 20000 | E9: 20000 | F9: Verify actual fees with CA/OCR/IRD
A10: Marketing & sales materials (launch) | B10: 12000 | C10: 25000 | D10: 25000 | E10: 25000 | F10: Sample kits, catalogue, boosted posts
A11: Website & communication tools | B11: 5000 | C11: 10000 | D11: 10000 | E11: 10000 | F11: Simple site, WhatsApp Business, domain
A12: Delivery setup | B12: 0 | C12: 10000 | D12: 10000 | E12: 10000 | F12: Boxes, tape, courier account
A13: Equipment: label/sticker cutter, landed (ONLY after pilot gate) | B13: 0 | C13: 0 | D13: 0 | E13: 250000 | F13: See Machinery sheet; landed estimate, low confidence
A14: Subtotal - set-up spend | B14: =SUM(B2:B13) -> 72000 | C14: =SUM(C2:C13) -> 265000 | D14: =SUM(D2:D13) -> 185000 | E14: =SUM(E2:E13) -> 515000
A15: Working capital reserve | B15: 60000 | C15: 185000 | D15: =C15+(C2-D2)+(C6-D6) -> 265000 | E15: 185000
A16: Contingency | B16: 18000 | C16: 50000 | D16: 50000 | E16: 50000
A17: TOTAL CASH REQUIRED | B17: =B14+B15+B16 -> 150000 | C17: =C14+C15+C16 -> 500000 | D17: =D14+D15+D16 -> 500000 | E17: =E14+E15+E16 -> 750000
A18: Within NPR 5,00,000 ceiling? | B18: =IF(B17<=Assumptions!$B$2,"YES","NO - exceeds by "&TEXT(B17-Assumptions!$B$2,"#,##0")) -> YES | C18: =IF(C17<=Assumptions!$B$2,"YES","NO - exceeds by "&TEXT(C17-Assumptions!$B$2,"#,##0")) -> YES | D18: =IF(D17<=Assumptions!$B$2,"YES","NO - exceeds by "&TEXT(D17-Assumptions!$B$2,"#,##0")) -> YES | E18: =IF(E17<=Assumptions!$B$2,"YES","NO - exceeds by "&TEXT(E17-Assumptions!$B$2,"#,##0")) -> NO - exceeds by 250,000
A20: Opening operating cash (WC + contingency) - recommended config | C20: =C15+C16 -> 235000
A21: Config C is shown to demonstrate that powered equipment does not fit the ceiling with a safe reserve; it is NOT a recommendation.
A22: Config B-own is a reallocation scenario: laptop and premises deposit saved are moved to working capital.

Sheet Machinery
A1: Category | B1: Item / listing (as advertised, NOT quoted) | C1: New/Used | D1: Advertised price (INR) | E1: Landed uplift % (assumed freight+duty+install) | F1: Advertised in NPR | G1: Est. landed NPR | H1: In recommended config? | I1: Status | J1: Confidence | K1: Source / note
A2: Cutting plotter | B2: Roland GS2-24 (listing) | C2: New | D2: 119000 | E2: 0.25 | F2: =D2*Assumptions!$B$3/100 -> 190578.5 | G2: =F2*(1+E2) -> 238223.12 | H2: No - post-pilot gate | I2: Advertised only | J2: Low | K2: IndiaMART listing surfaced in search 2026-10-23 (snippet only, not page-verified): https://m.indiamart.com/proddetail/digital-plotter-printer-15957722430.html
A3: Cutting plotter | B3: Radium cutting plotter (Om Trading, New Delhi) | C3: New | D3: 127000 | E3: 0.25 | F3: =D3*Assumptions!$B$3/100 -> 203390.5 | G3: =F3*(1+E3) -> 254238.12 | H3: No - post-pilot gate | I3: Advertised only | J3: Low | K3: https://m.indiamart.com/proddetail/plotter-printer-20127469462.html (price from search snippet)
A4: Label cutter | B4: Sticker half-cutter (Delhi-NCR seller) | C4: New | D4: 115000 | E4: 0.25 | F4: =D4*Assumptions!$B$3/100 -> 184172.5 | G4: =F4*(1+E4) -> 230215.62 | H4: No - post-pilot gate | I4: Advertised only | J4: Low | K4: Search snippet via https://m.indiamart.com/digitalprint-solutions/label-cutters.html; per-listing attribution unverified
A5: Label cutter | B5: Servo-motor label cutter | C5: New | D5: 190000 | E5: 0.25 | F5: =D5*Assumptions!$B$3/100 -> 304285 | G5: =F5*(1+E5) -> 380356.25 | H5: No | I5: Advertised only | J5: Low | K5: Same source as above; attribution unverified
A6: Die cutter | B6: Sticker cutting machine (C Press, Chennai) | C6: New | D6: 150000 | E6: 0.25 | F6: =D6*Assumptions!$B$3/100 -> 240225 | G6: =F6*(1+E6) -> 300281.25 | H6: No | I6: Advertised only | J6: Low | K6: https://m.indiamart.com/cpress-chennai/die-cutting-machine.html (snippet)
A7: Digital half-cutter | B7: Digital sticker half-cutting machine (C Press) | C7: New | D7: 450000 | E7: 0.25 | F7: =D7*Assumptions!$B$3/100 -> 720675 | G7: =F7*(1+E7) -> 900843.75 | H7: No - exceeds sensible share of budget | I7: Advertised only | J7: Low | K7: https://m.indiamart.com/cpress-chennai/die-cutting-machine.html (snippet)
A8: Wide-format printer | B8: Epson T3130n 24in (Bengaluru, used) | C8: Used | D8: 95000 | E8: 0.25 | F8: =D8*Assumptions!$B$3/100 -> 152142.5 | G8: =F8*(1+E8) -> 190178.12 | H8: No - not suited to packaging substrates | I8: Advertised only | J8: Low | K8: Search snippet, IndiaMART; used equipment, condition unverified
A9: Wide-format printer | B9: HP DesignJet Z6dr 44in | C9: New/Used? | D9: 285000 | E9: 0.25 | F9: =D9*Assumptions!$B$3/100 -> 456427.5 | G9: =F9*(1+E9) -> 570534.38 | H9: No | I9: Advertised only | J9: Low | K9: Search snippet, IndiaMART; condition not stated
A11: Not found / not verified: Nepal customs duty and VAT on printing/cutting machinery (HS 8443 / 8441 / 8479); local Nepal dealer prices; warranty and service terms; power specifications.
A12: Landed uplift of 25% is a placeholder assumption, NOT a researched rate. Get a customs-agent quote before any purchase.
A13: Recommendation: buy NO powered machine until the 90-day pilot gate is passed (see 12_final_investment_recommendation.md).

Sheet Product_Pricing
A1: Product | B1: Qty | C1: Supplier unit cost | D1: Supplier setup/die/plate (one-off) | E1: Internal design & sample labour (NPR) | F1: Delivery per order | G1: Wastage % of supplier cost | H1: Unit selling price | I1: Design fee charged | J1: Setup fee charged to customer (=1.15 x supplier setup) | K1: Revenue (ex-VAT) | L1: Supplier cost incl. wastage + setup | M1: Gross profit (after design labour) | N1: Gross margin | O1: Financing/payment cost (1.5% rev) | P1: Contribution | Q1: Contribution margin | R1: Meets min contribution? | S1: MOQ tier flag | T1: Mix weight (share of orders) | U1: Cash gross margin (excl. founder design time)
A2: 1 Kraft paper bag, 1-colour logo | B2: 100 | C2: 45 | D2: 2500 | E2: 1500 | F2: 500 | G2: 0.03 | H2: 68 | I2: 0 | J2: =1.15*D2 -> 2875 | K2: =B2*H2+I2+J2 -> 9675 | L2: =B2*C2*(1+G2)+D2 -> 7135 | M2: =K2-L2-E2 -> 1040 | N2: =M2/K2 -> 0.10749354 | O2: =0.015*K2 -> 145.125 | P2: =M2-F2-O2 -> 394.875 | Q2: =P2/K2 -> 0.040813953 | R2: =IF(P2>=Assumptions!$B$25,"YES","NO") -> NO | S2: =IF(AND(R2="YES",OR(A2<>A1,R1<>"YES")),1,0) -> 0 | T2: 0.25 | U2: =(M2+E2)/K2 -> 0.2625323
A3: 1 Kraft paper bag, 1-colour logo | B3: 250 | C3: 34 | D3: 2500 | E3: 1500 | F3: 500 | G3: 0.03 | H3: 52 | I3: 0 | J3: =1.15*D3 -> 2875 | K3: =B3*H3+I3+J3 -> 15875 | L3: =B3*C3*(1+G3)+D3 -> 11255 | M3: =K3-L3-E3 -> 3120 | N3: =M3/K3 -> 0.19653543 | O3: =0.015*K3 -> 238.125 | P3: =M3-F3-O3 -> 2381.875 | Q3: =P3/K3 -> 0.15003937 | R3: =IF(P3>=Assumptions!$B$25,"YES","NO") -> NO | S3: =IF(AND(R3="YES",OR(A3<>A2,R2<>"YES")),1,0) -> 0 | T3: 0.25 | U3: =(M3+E3)/K3 -> 0.29102362
A4: 1 Kraft paper bag, 1-colour logo | B4: 500 | C4: 28 | D4: 2500 | E4: 1500 | F4: 500 | G4: 0.03 | H4: 42 | I4: 0 | J4: =1.15*D4 -> 2875 | K4: =B4*H4+I4+J4 -> 23875 | L4: =B4*C4*(1+G4)+D4 -> 16920 | M4: =K4-L4-E4 -> 5455 | N4: =M4/K4 -> 0.22848168 | O4: =0.015*K4 -> 358.125 | P4: =M4-F4-O4 -> 4596.875 | Q4: =P4/K4 -> 0.19253927 | R4: =IF(P4>=Assumptions!$B$25,"YES","NO") -> YES | S4: =IF(AND(R4="YES",OR(A4<>A3,R3<>"YES")),1,0) -> 1 | T4: 0.25 | U4: =(M4+E4)/K4 -> 0.2913089
A5: 1 Kraft paper bag, 1-colour logo | B5: 1000 | C5: 23 | D5: 2500 | E5: 1500 | F5: 500 | G5: 0.03 | H5: 34 | I5: 0 | J5: =1.15*D5 -> 2875 | K5: =B5*H5+I5+J5 -> 36875 | L5: =B5*C5*(1+G5)+D5 -> 26190 | M5: =K5-L5-E5 -> 9185 | N5: =M5/K5 -> 0.24908475 | O5: =0.015*K5 -> 553.125 | P5: =M5-F5-O5 -> 8131.875 | Q5: =P5/K5 -> 0.22052542 | R5: =IF(P5>=Assumptions!$B$25,"YES","NO") -> YES | S5: =IF(AND(R5="YES",OR(A5<>A4,R4<>"YES")),1,0) -> 0 | T5: 0.25 | U5: =(M5+E5)/K5 -> 0.28976271
A6: 1 Kraft paper bag, 1-colour logo | B6: 5000 | C6: 19 | D6: 2500 | E6: 1500 | F6: 500 | G6: 0.03 | H6: 28 | I6: 0 | J6: =1.15*D6 -> 2875 | K6: =B6*H6+I6+J6 -> 142875 | L6: =B6*C6*(1+G6)+D6 -> 100350 | M6: =K6-L6-E6 -> 41025 | N6: =M6/K6 -> 0.28713911 | O6: =0.015*K6 -> 2143.125 | P6: =M6-F6-O6 -> 38381.875 | Q6: =P6/K6 -> 0.26863955 | R6: =IF(P6>=Assumptions!$B$25,"YES","NO") -> YES | S6: =IF(AND(R6="YES",OR(A6<>A5,R5<>"YES")),1,0) -> 0 | T6: 0.25 | U6: =(M6+E6)/K6 -> 0.2976378
A7: 2 Folding carton, 4-colour | B7: 100 | C7: 95 | D7: 9000 | E7: 3500 | F7: 700 | G7: 0.03 | H7: 150 | I7: 3000 | J7: =1.15*D7 -> 10350 | K7: =B7*H7+I7+J7 -> 28350 | L7: =B7*C7*(1+G7)+D7 -> 18785 | M7: =K7-L7-E7 -> 6065 | N7: =M7/K7 -> 0.21393298 | O7: =0.015*K7 -> 425.25 | P7: =M7-F7-O7 -> 4939.75 | Q7: =P7/K7 -> 0.17424162 | R7: =IF(P7>=Assumptions!$B$25,"YES","NO") -> YES | S7: =IF(AND(R7="YES",OR(A7<>A6,R6<>"YES")),1,0) -> 1 | T7: 0.2 | U7: =(M7+E7)/K7 -> 0.33738977
A8: 2 Folding carton, 4-colour | B8: 250 | C8: 62 | D8: 9000 | E8: 3500 | F8: 700 | G8: 0.03 | H8: 96 | I8: 3000 | J8: =1.15*D8 -> 10350 | K8: =B8*H8+I8+J8 -> 37350 | L8: =B8*C8*(1+G8)+D8 -> 24965 | M8: =K8-L8-E8 -> 8885 | N8: =M8/K8 -> 0.23788487 | O8: =0.015*K8 -> 560.25 | P8: =M8-F8-O8 -> 7624.75 | Q8: =P8/K8 -> 0.20414324 | R8: =IF(P8>=Assumptions!$B$25,"YES","NO") -> YES | S8: =IF(AND(R8="YES",OR(A8<>A7,R7<>"YES")),1,0) -> 0 | T8: 0.2 | U8: =(M8+E8)/K8 -> 0.33159304
A9: 2 Folding carton, 4-colour | B9: 500 | C9: 42 | D9: 9000 | E9: 3500 | F9: 700 | G9: 0.03 | H9: 64 | I9: 3000 | J9: =1.15*D9 -> 10350 | K9: =B9*H9+I9+J9 -> 45350 | L9: =B9*C9*(1+G9)+D9 -> 30630 | M9: =K9-L9-E9 -> 11220 | N9: =M9/K9 -> 0.24740904 | O9: =0.015*K9 -> 680.25 | P9: =M9-F9-O9 -> 9839.75 | Q9: =P9/K9 -> 0.21697354 | R9: =IF(P9>=Assumptions!$B$25,"YES","NO") -> YES | S9: =IF(AND(R9="YES",OR(A9<>A8,R8<>"YES")),1,0) -> 0 | T9: 0.2 | U9: =(M9+E9)/K9 -> 0.32458655
A10: 2 Folding carton, 4-colour | B10: 1000 | C10: 30 | D10: 9000 | E10: 3500 | F10: 700 | G10: 0.03 | H10: 46 | I10: 3000 | J10: =1.15*D10 -> 10350 | K10: =B10*H10+I10+J10 -> 59350 | L10: =B10*C10*(1+G10)+D10 -> 39900 | M10: =K10-L10-E10 -> 15950 | N10: =M10/K10 -> 0.26874473 | O10: =0.015*K10 -> 890.25 | P10: =M10-F10-O10 -> 14359.75 | Q10: =P10/K10 -> 0.24195029 | R10: =IF(P10>=Assumptions!$B$25,"YES","NO") -> YES | S10: =IF(AND(R10="YES",OR(A10<>A9,R9<>"YES")),1,0) -> 0 | T10: 0.2 | U10: =(M10+E10)/K10 -> 0.32771693
A11: 2 Folding carton, 4-colour | B11: 5000 | C11: 20 | D11: 9000 | E11: 3500 | F11: 700 | G11: 0.03 | H11: 31 | I11: 3000 | J11: =1.15*D11 -> 10350 | K11: =B11*H11+I11+J11 -> 168350 | L11: =B11*C11*(1+G11)+D11 -> 112000 | M11: =K11-L11-E11 -> 52850 | N11: =M11/K11 -> 0.31392931 | O11: =0.015*K11 -> 2525.25 | P11: =M11-F11-O11 -> 49624.75 | Q11: =P11/K11 -> 0.29477131 | R11: =IF(P11>=Assumptions!$B$25,"YES","NO") -> YES | S11: =IF(AND(R11="YES",OR(A11<>A10,R10<>"YES")),1,0) -> 0 | T11: 0.2 | U11: =(M11+E11)/K11 -> 0.33471933
A12: 3 Printed corrugated mailer box | B12: 100 | C12: 85 | D12: 4000 | E12: 2000 | F12: 700 | G12: 0.03 | H12: 125 | I12: 1500 | J12: =1.15*D12 -> 4600 | K12: =B12*H12+I12+J12 -> 18600 | L12: =B12*C12*(1+G12)+D12 -> 12755 | M12: =K12-L12-E12 -> 3845 | N12: =M12/K12 -> 0.20672043 | O12: =0.015*K12 -> 279 | P12: =M12-F12-O12 -> 2866 | Q12: =P12/K12 -> 0.15408602 | R12: =IF(P12>=Assumptions!$B$25,"YES","NO") -> NO | S12: =IF(AND(R12="YES",OR(A12<>A11,R11<>"YES")),1,0) -> 0 | T12: 0.2 | U12: =(M12+E12)/K12 -> 0.31424731
A13: 3 Printed corrugated mailer box | B13: 250 | C13: 64 | D13: 4000 | E13: 2000 | F13: 700 | G13: 0.03 | H13: 95 | I13: 1500 | J13: =1.15*D13 -> 4600 | K13: =B13*H13+I13+J13 -> 29850 | L13: =B13*C13*(1+G13)+D13 -> 20480 | M13: =K13-L13-E13 -> 7370 | N13: =M13/K13 -> 0.24690117 | O13: =0.015*K13 -> 447.75 | P13: =M13-F13-O13 -> 6222.25 | Q13: =P13/K13 -> 0.20845059 | R13: =IF(P13>=Assumptions!$B$25,"YES","NO") -> YES | S13: =IF(AND(R13="YES",OR(A13<>A12,R12<>"YES")),1,0) -> 1 | T13: 0.2 | U13: =(M13+E13)/K13 -> 0.31390285
... A31: 6 Bakery/takeaway box, printed | B31: 5000 | C31: 15 | D31: 5000 | E31: 1500 | F31: 600 | G31: 0.03 | H31: 21 | I31: 1000 | J31: =1.15*D31 -> 5750 | K31: =B31*H31+I31+J31 -> 111750 | L31: =B31*C31*(1+G31)+D31 -> 82250 | M31: =K31-L31-E31 -> 28000 | N31: =M31/K31 -> 0.25055928 | O31: =0.015*K31 -> 1676.25 | P31: =M31-F31-O31 -> 25723.75 | Q31: =P31/K31 -> 0.23019016 | R31: =IF(P31>=Assumptions!$B$25,"YES","NO") -> YES | S31: =IF(AND(R31="YES",OR(A31<>A30,R30<>"YES")),1,0) -> 0 | T31: 0.2 | U31: =(M31+E31)/K31 -> 0.2639821
A33: ALL supplier costs, setup charges and selling prices are ASSUMPTIONS (confidence LOW). Only verified local price points: The Box House Nepal retail - pastry box NPR 10, 2lb cake box NPR 35, 12in pizza box NPR 20 (unprinted stock; boxhousenepal.com.np, 2026-10-23).
A34: VAT (13%) is excluded from revenue. Customer-facing quotes add VAT only if the business is VAT-registered.
A35: Pricing policy modelled: setup/die/plate charged to customer at 1.15x supplier charge; design fee on custom structures; orders below minimum contribution are refused or re-quoted at the next tier.

Sheet Engine
A1: ENGINE: Downside | P1: Collection lag (months) | Q1: =MAX(1,ROUNDUP((Assumptions!$B$10+Scenario_Inputs!$F$3)/30,0)) -> 2
A2: Month | C2: 1 | D2: 2 | E2: 3 | F2: 4 | G2: 5 | H2: 6 | I2: 7 | J2: 8 | K2: 9 | L2: 10 | M2: 11 | N2: 12 | O2: 12-mo total
A3: New customers | C3: =Assumptions!B$33*Scenario_Inputs!$D$3 -> 0 | D3: =Assumptions!C$33*Scenario_Inputs!$D$3 -> 0.5 | E3: =Assumptions!D$33*Scenario_Inputs!$D$3 -> 1 | F3: =Assumptions!E$33*Scenario_Inputs!$D$3 -> 1.5 | G3: =Assumptions!F$33*Scenario_Inputs!$D$3 -> 1.5 | H3: =Assumptions!G$33*Scenario_Inputs!$D$3 -> 2 | I3: =Assumptions!H$33*Scenario_Inputs!$D$3 -> 2 | J3: =Assumptions!I$33*Scenario_Inputs!$D$3 -> 2.5 | ... N3: =Assumptions!M$33*Scenario_Inputs!$D$3 -> 3 | O3: =SUM(C3:N3) -> 22
A4: Customers at start of month | C4: 0 | D4: =SUM($C3:C3) -> 0 | E4: =SUM($C3:D3) -> 0.5 | F4: =SUM($C3:E3) -> 1.5 | G4: =SUM($C3:F3) -> 3 | H4: =SUM($C3:G3) -> 4.5 | I4: =SUM($C3:H3) -> 6.5 | J4: =SUM($C3:I3) -> 8.5 | K4: =SUM($C3:J3) -> 11 | ... N4: =SUM($C3:M3) -> 19
A5: Repeat orders | C5: =C4*Assumptions!$B$11*Scenario_Inputs!$E$3 -> 0 | D5: =D4*Assumptions!$B$11*Scenario_Inputs!$E$3 -> 0 | E5: =E4*Assumptions!$B$11*Scenario_Inputs!$E$3 -> 0.054 | F5: =F4*Assumptions!$B$11*Scenario_Inputs!$E$3 -> 0.162 | G5: =G4*Assumptions!$B$11*Scenario_Inputs!$E$3 -> 0.324 | H5: =H4*Assumptions!$B$11*Scenario_Inputs!$E$3 -> 0.486 | I5: =I4*Assumptions!$B$11*Scenario_Inputs!$E$3 -> 0.702 | J5: =J4*Assumptions!$B$11*Scenario_Inputs!$E$3 -> 0.918 | ... N5: =N4*Assumptions!$B$11*Scenario_Inputs!$E$3 -> 2.052 | O5: =SUM(C5:N5) -> 9.072
A6: Total orders | C6: =C3+C5 -> 0 | D6: =D3+D5 -> 0.5 | E6: =E3+E5 -> 1.054 | F6: =F3+F5 -> 1.662 | G6: =G3+G5 -> 1.824 | H6: =H3+H5 -> 2.486 | I6: =I3+I5 -> 2.702 | J6: =J3+J5 -> 3.418 | ... N6: =N3+N5 -> 5.052 | O6: =SUM(C6:N6) -> 31.072
A7: Base revenue (pre price shock) | C7: =C6*Assumptions!$B$5*Scenario_Inputs!G$4 -> 0 | D7: =D6*Assumptions!$B$5*Scenario_Inputs!H$4 -> 13359.375 | E7: =E6*Assumptions!$B$5*Scenario_Inputs!I$4 -> 28161.562 | F7: =F6*Assumptions!$B$5*Scenario_Inputs!J$4 -> 44406.562 | G7: =G6*Assumptions!$B$5*Scenario_Inputs!K$4 -> 48735 | H7: =H6*Assumptions!$B$5*Scenario_Inputs!L$4 -> 66422.812 | I7: =I6*Assumptions!$B$5*Scenario_Inputs!M$4 -> 72194.062 | J7: =J6*Assumptions!$B$5*Scenario_Inputs!N$4 -> 91324.688 | ... N7: =N6*Assumptions!$B$5*Scenario_Inputs!R$4 -> 134983.12 | O7: =SUM(C7:N7) -> 830205
A8: Revenue | C8: =C7*Scenario_Inputs!$B$3 -> 0 | D8: =D7*Scenario_Inputs!$B$3 -> 13359.375 | E8: =E7*Scenario_Inputs!$B$3 -> 28161.562 | F8: =F7*Scenario_Inputs!$B$3 -> 44406.562 | G8: =G7*Scenario_Inputs!$B$3 -> 48735 | H8: =H7*Scenario_Inputs!$B$3 -> 66422.812 | I8: =I7*Scenario_Inputs!$B$3 -> 72194.062 | J8: =J7*Scenario_Inputs!$B$3 -> 91324.688 | ... N8: =N7*Scenario_Inputs!$B$3 -> 134983.12 | O8: =SUM(C8:N8) -> 830205
A9: Supplier cost | C9: =C7*(1-Assumptions!$B$6)*Scenario_Inputs!$C$3*(1+(1-Assumptions!$B$26)*Assumptions!$B$21*Assumptions!$B$27) -> 0 | D9: =D7*(1-Assumptions!$B$6)*Scenario_Inputs!$C$3*(1+(1-Assumptions!$B$26)*Assumptions!$B$21*Assumptions!$B$27) -> 10833.765 | E9: =E7*(1-Assumptions!$B$6)*Scenario_Inputs!$C$3*(1+(1-Assumptions!$B$26)*Assumptions!$B$21*Assumptions!$B$27) -> 22837.577 | F9: =F7*(1-Assumptions!$B$6)*Scenario_Inputs!$C$3*(1+(1-Assumptions!$B$26)*Assumptions!$B$21*Assumptions!$B$27) -> 36011.436 | G9: =G7*(1-Assumptions!$B$6)*Scenario_Inputs!$C$3*(1+(1-Assumptions!$B$26)*Assumptions!$B$21*Assumptions!$B$27) -> 39521.576 | H9: =H7*(1-Assumptions!$B$6)*Scenario_Inputs!$C$3*(1+(1-Assumptions!$B$26)*Assumptions!$B$21*Assumptions!$B$27) -> 53865.481 | I9: =I7*(1-Assumptions!$B$6)*Scenario_Inputs!$C$3*(1+(1-Assumptions!$B$26)*Assumptions!$B$21*Assumptions!$B$27) -> 58545.667 | J9: =J7*(1-Assumptions!$B$6)*Scenario_Inputs!$C$3*(1+(1-Assumptions!$B$26)*Assumptions!$B$21*Assumptions!$B$27) -> 74059.619 | ... N9: =N7*(1-Assumptions!$B$6)*Scenario_Inputs!$C$3*(1+(1-Assumptions!$B$26)*Assumptions!$B$21*Assumptions!$B$27) -> 109464.36 | O9: =SUM(C9:N9) -> 673253.51
A10: Other variable (delivery/fees/rework) | C10: =C8*(Assumptions!$B$7+Assumptions!$B$8) -> 0 | D10: =D8*(Assumptions!$B$7+Assumptions!$B$8) -> 801.5625 | E10: =E8*(Assumptions!$B$7+Assumptions!$B$8) -> 1689.6937 | F10: =F8*(Assumptions!$B$7+Assumptions!$B$8) -> 2664.3938 | G10: =G8*(Assumptions!$B$7+Assumptions!$B$8) -> 2924.1 | H10: =H8*(Assumptions!$B$7+Assumptions!$B$8) -> 3985.3688 | I10: =I8*(Assumptions!$B$7+Assumptions!$B$8) -> 4331.6438 | J10: =J8*(Assumptions!$B$7+Assumptions!$B$8) -> 5479.4812 | ... N10: =N8*(Assumptions!$B$7+Assumptions!$B$8) -> 8098.9875 | O10: =SUM(C10:N10) -> 49812.3
A11: Contribution | C11: =C8-C9-C10 -> 0 | D11: =D8-D9-D10 -> 1724.0473 | E11: =E8-E9-E10 -> 3634.2916 | F11: =F8-F9-F10 -> 5730.7331 | G11: =G8-G9-G10 -> 6289.3244 | H11: =H8-H9-H10 -> 8571.9629 | I11: =I8-I9-I10 -> 9316.7513 | J11: =J8-J9-J10 -> 11785.587 | ... N11: =N8-N9-N10 -> 17419.773 | O11: =SUM(C11:N11) -> 107139.19
A12: Fixed opex | C12: =Assumptions!$B$29 -> 32500 | D12: =Assumptions!$B$29 -> 32500 | E12: =Assumptions!$B$29 -> 32500 | F12: =Assumptions!$B$29 -> 32500 | G12: =Assumptions!$B$29 -> 32500 | H12: =Assumptions!$B$29 -> 32500 | I12: =Assumptions!$B$29 -> 32500 | J12: =Assumptions!$B$29 -> 32500 | ... N12: =Assumptions!$B$29 -> 32500 | O12: =SUM(C12:N12) -> 390000
A13: One-off costs | C13: =Scenario_Inputs!G$5 -> 0 | D13: =Scenario_Inputs!H$5 -> 0 | E13: =Scenario_Inputs!I$5 -> 0 | F13: =Scenario_Inputs!J$5 -> 0 | G13: =Scenario_Inputs!K$5 -> 0 | H13: =Scenario_Inputs!L$5 -> 0 | I13: =Scenario_Inputs!M$5 -> 0 | J13: =Scenario_Inputs!N$5 -> 0 | ... N13: =Scenario_Inputs!R$5 -> 0 | O13: =SUM(C13:N13) -> 0
A14: Operating profit BEFORE founder pay | C14: =C11-C12-C13 -> -32500 | D14: =D11-D12-D13 -> -30775.953 | E14: =E11-E12-E13 -> -28865.708 | F14: =F11-F12-F13 -> -26769.267 | G14: =G11-G12-G13 -> -26210.676 | H14: =H11-H12-H13 -> -23928.037 | I14: =I11-I12-I13 -> -23183.249 | J14: =J11-J12-J13 -> -20714.413 | ... N14: =N11-N12-N13 -> -15080.227 | O14: =SUM(C14:N14) -> -282860.81
A15: Founder compensation | C15: =IF(C2>=Assumptions!$B$13,Assumptions!$B$12,0) -> 0 | D15: =IF(D2>=Assumptions!$B$13,Assumptions!$B$12,0) -> 0 | E15: =IF(E2>=Assumptions!$B$13,Assumptions!$B$12,0) -> 0 | F15: =IF(F2>=Assumptions!$B$13,Assumptions!$B$12,0) -> 0 | G15: =IF(G2>=Assumptions!$B$13,Assumptions!$B$12,0) -> 0 | H15: =IF(H2>=Assumptions!$B$13,Assumptions!$B$12,0) -> 0 | I15: =IF(I2>=Assumptions!$B$13,Assumptions!$B$12,0) -> 15000 | J15: =IF(J2>=Assumptions!$B$13,Assumptions!$B$12,0) -> 15000 | ... N15: =IF(N2>=Assumptions!$B$13,Assumptions!$B$12,0) -> 15000 | O15: =SUM(C15:N15) -> 90000
A16: Operating profit AFTER founder pay | C16: =C14-C15 -> -32500 | D16: =D14-D15 -> -30775.953 | E16: =E14-E15 -> -28865.708 | F16: =F14-F15 -> -26769.267 | G16: =G14-G15 -> -26210.676 | H16: =H14-H15 -> -23928.037 | I16: =I14-I15 -> -38183.249 | J16: =J14-J15 -> -35714.413 | ... N16: =N14-N15 -> -30080.227 | O16: =SUM(C16:N16) -> -372860.81
A17: Cash receipts | C17: =Assumptions!$B$9*C8+(1-Assumptions!$B$9)*IF(C2-$Q$1>=1,INDEX($C8:$N8,C2-$Q$1),0) -> 0 | D17: =Assumptions!$B$9*D8+(1-Assumptions!$B$9)*IF(D2-$Q$1>=1,INDEX($C8:$N8,D2-$Q$1),0) -> 6679.6875 | E17: =Assumptions!$B$9*E8+(1-Assumptions!$B$9)*IF(E2-$Q$1>=1,INDEX($C8:$N8,E2-$Q$1),0) -> 14080.781 | F17: =Assumptions!$B$9*F8+(1-Assumptions!$B$9)*IF(F2-$Q$1>=1,INDEX($C8:$N8,F2-$Q$1),0) -> 28882.969 | G17: =Assumptions!$B$9*G8+(1-Assumptions!$B$9)*IF(G2-$Q$1>=1,INDEX($C8:$N8,G2-$Q$1),0) -> 38448.281 | H17: =Assumptions!$B$9*H8+(1-Assumptions!$B$9)*IF(H2-$Q$1>=1,INDEX($C8:$N8,H2-$Q$1),0) -> 55414.688 | I17: =Assumptions!$B$9*I8+(1-Assumptions!$B$9)*IF(I2-$Q$1>=1,INDEX($C8:$N8,I2-$Q$1),0) -> 60464.531 | J17: =Assumptions!$B$9*J8+(1-Assumptions!$B$9)*IF(J2-$Q$1>=1,INDEX($C8:$N8,J2-$Q$1),0) -> 78873.75 | ... N17: =Assumptions!$B$9*N8+(1-Assumptions!$B$9)*IF(N2-$Q$1>=1,INDEX($C8:$N8,N2-$Q$1),0) -> 120367.97 | O17: =SUM(C17:N17) -> 699550.31
A18: Cash payments | C18: =C9+C10+C12+C13+C15 -> 32500 | D18: =D9+D10+D12+D13+D15 -> 44135.328 | E18: =E9+E10+E12+E13+E15 -> 57027.271 | F18: =F9+F10+F12+F13+F15 -> 71175.829 | G18: =G9+G10+G12+G13+G15 -> 74945.676 | H18: =H9+H10+H12+H13+H15 -> 90350.85 | I18: =I9+I10+I12+I13+I15 -> 110377.31 | J18: =J9+J10+J12+J13+J15 -> 127039.1 | ... N18: =N9+N10+N12+N13+N15 -> 165063.35 | O18: =SUM(C18:N18) -> 1203065.8
A19: Net cash flow | C19: =C17-C18 -> -32500 | D19: =D17-D18 -> -37455.64 | E19: =E17-E18 -> -42946.49 | F19: =F17-F18 -> -42292.861 | G19: =G17-G18 -> -36497.394 | H19: =H17-H18 -> -34936.162 | I19: =I17-I18 -> -49912.78 | J19: =J17-J18 -> -48165.35 | ... N19: =N17-N18 -> -44695.383 | O19: =SUM(C19:N19) -> -503515.5
A20: Closing cash | C20: =Capital_Allocation!$C$20+C19 -> 202500 | D20: =C20+D19 -> 165044.36 | E20: =D20+E19 -> 122097.87 | F20: =E20+F19 -> 79805.009 | G20: =F20+G19 -> 43307.615 | H20: =G20+H19 -> 8371.453 | I20: =H20+I19 -> -41541.327 | J20: =I20+J19 -> -89706.677 | K20: =J20+K19 -> -137662.45 | ... N20: =M20+N19 -> -268515.5
A21: Receivables balance | C21: =SUM($C8:C8)-SUM($C17:C17) -> 0 | D21: =SUM($C8:D8)-SUM($C17:D17) -> 6679.6875 | E21: =SUM($C8:E8)-SUM($C17:E17) -> 20760.469 | F21: =SUM($C8:F8)-SUM($C17:F17) -> 36284.062 | G21: =SUM($C8:G8)-SUM($C17:G17) -> 46570.781 | H21: =SUM($C8:H8)-SUM($C17:H17) -> 57578.906 | I21: =SUM($C8:I8)-SUM($C17:I17) -> 69308.438 | J21: =SUM($C8:J8)-SUM($C17:J17) -> 81759.375 | ... N21: =SUM($C8:N8)-SUM($C17:N17) -> 130654.69
A22: Cumulative profit after founder | C22: =SUM($C16:C16) -> -32500 | D22: =SUM($C16:D16) -> -63275.953 | E22: =SUM($C16:E16) -> -92141.661 | F22: =SUM($C16:F16) -> -118910.93 | G22: =SUM($C16:G16) -> -145121.6 | H22: =SUM($C16:H16) -> -169049.64 | I22: =SUM($C16:I16) -> -207232.89 | J22: =SUM($C16:J16) -> -242947.3 | ... N22: =SUM($C16:N16) -> -372860.81
A23: Break-even flag (profit after founder >=0 -> month, else 99) | C23: =IF(C16>=0,C2,99) -> 99 | D23: =IF(D16>=0,D2,99) -> 99 | E23: =IF(E16>=0,E2,99) -> 99 | F23: =IF(F16>=0,F2,99) -> 99 | G23: =IF(G16>=0,G2,99) -> 99 | H23: =IF(H16>=0,H2,99) -> 99 | I23: =IF(I16>=0,I2,99) -> 99 | J23: =IF(J16>=0,J2,99) -> 99 | ... N23: =IF(N16>=0,N2,99) -> 99
A24: Break-even flag BEFORE founder (profit >=0 -> month, else 99) | C24: =IF(C14>=0,C2,99) -> 99 | D24: =IF(D14>=0,D2,99) -> 99 | E24: =IF(E14>=0,E2,99) -> 99 | F24: =IF(F14>=0,F2,99) -> 99 | G24: =IF(G14>=0,G2,99) -> 99 | H24: =IF(H14>=0,H2,99) -> 99 | I24: =IF(I14>=0,I2,99) -> 99 | J24: =IF(J14>=0,J2,99) -> 99 | ... N24: =IF(N14>=0,N2,99) -> 99
A25: Total revenue | B25: =O8 -> 830205
A26: Total contribution | B26: =O11 -> 107139.19
A27: Total operating profit after founder | B27: =O16 -> -372860.81
A28: Minimum closing cash | B28: =MIN(C20:N20) -> -268515.5
A29: Ending cash (month 12) | B29: =N20 -> -268515.5
A30: Solvent within ceiling (cash never < 0)? | B30: =IF(B28>=0,"YES","NO") -> NO
A31: Solvent WITHOUT using contingency? | B31: =IF(B28>=Capital_Allocation!$C$16,"YES","NO") -> NO
A32: First month op. profit >= 0 BEFORE founder pay | B32: =IF(MIN(C24:N24)=99,"none in 12 mo",MIN(C24:N24)) -> none in 12 mo
A33: Month-12 operating profit AFTER founder pay | B33: =N16 -> -30080.227
A34: Month-12 receivables | B34: =N21 -> 130654.69
A35: First month op. profit >= 0 AFTER founder pay | B35: =IF(MIN(C23:N23)=99,"none in 12 mo",MIN(C23:N23)) -> none in 12 mo
A39: ENGINE: Base | P39: Collection lag (months) | Q39: =MAX(1,ROUNDUP((Assumptions!$B$10+Scenario_Inputs!$F$7)/30,0)) -> 1
A40: Month | C40: 1 | D40: 2 | E40: 3 | F40: 4 | G40: 5 | H40: 6 | I40: 7 | J40: 8 | K40: 9 | L40: 10 | M40: 11 | N40: 12 | O40: 12-mo total
A41: New customers | C41: =Assumptions!B$33*Scenario_Inputs!$D$7 -> 0 | D41: =Assumptions!C$33*Scenario_Inputs!$D$7 -> 1 | E41: =Assumptions!D$33*Scenario_Inputs!$D$7 -> 2 | F41: =Assumptions!E$33*Scenario_Inputs!$D$7 -> 3 | G41: =Assumptions!F$33*Scenario_Inputs!$D$7 -> 3 | H41: =Assumptions!G$33*Scenario_Inputs!$D$7 -> 4 | I41: =Assumptions!H$33*Scenario_Inputs!$D$7 -> 4 | J41: =Assumptions!I$33*Scenario_Inputs!$D$7 -> 5 | ... N41: =Assumptions!M$33*Scenario_Inputs!$D$7 -> 6 | O41: =SUM(C41:N41) -> 44
A42: Customers at start of month | C42: 0 | D42: =SUM($C41:C41) -> 0 | E42: =SUM($C41:D41) -> 1 | F42: =SUM($C41:E41) -> 3 | G42: =SUM($C41:F41) -> 6 | H42: =SUM($C41:G41) -> 9 | I42: =SUM($C41:H41) -> 13 | J42: =SUM($C41:I41) -> 17 | K42: =SUM($C41:J41) -> 22 | ... N42: =SUM($C41:M41) -> 38
A43: Repeat orders | C43: =C42*Assumptions!$B$11*Scenario_Inputs!$E$7 -> 0 | D43: =D42*Assumptions!$B$11*Scenario_Inputs!$E$7 -> 0 | E43: =E42*Assumptions!$B$11*Scenario_Inputs!$E$7 -> 0.18 | F43: =F42*Assumptions!$B$11*Scenario_Inputs!$E$7 -> 0.54 | G43: =G42*Assumptions!$B$11*Scenario_Inputs!$E$7 -> 1.08 | H43: =H42*Assumptions!$B$11*Scenario_Inputs!$E$7 -> 1.62 | I43: =I42*Assumptions!$B$11*Scenario_Inputs!$E$7 -> 2.34 | J43: =J42*Assumptions!$B$11*Scenario_Inputs!$E$7 -> 3.06 | ... N43: =N42*Assumptions!$B$11*Scenario_Inputs!$E$7 -> 6.84 | O43: =SUM(C43:N43) -> 30.24
A44: Total orders | C44: =C41+C43 -> 0 | D44: =D41+D43 -> 1 | E44: =E41+E43 -> 2.18 | F44: =F41+F43 -> 3.54 | G44: =G41+G43 -> 4.08 | H44: =H41+H43 -> 5.62 | I44: =I41+I43 -> 6.34 | J44: =J41+J43 -> 8.06 | ... N44: =N41+N43 -> 12.84 | O44: =SUM(C44:N44) -> 74.24
A45: Base revenue (pre price shock) | C45: =C44*Assumptions!$B$5*Scenario_Inputs!G$8 -> 0 | D45: =D44*Assumptions!$B$5*Scenario_Inputs!H$8 -> 26718.75 | E45: =E44*Assumptions!$B$5*Scenario_Inputs!I$8 -> 58246.875 | F45: =F44*Assumptions!$B$5*Scenario_Inputs!J$8 -> 94584.375 | G45: =G44*Assumptions!$B$5*Scenario_Inputs!K$8 -> 109012.5 | H45: =H44*Assumptions!$B$5*Scenario_Inputs!L$8 -> 150159.38 | I45: =I44*Assumptions!$B$5*Scenario_Inputs!M$8 -> 169396.88 | J45: =J44*Assumptions!$B$5*Scenario_Inputs!N$8 -> 215353.12 | ... N45: =N44*Assumptions!$B$5*Scenario_Inputs!R$8 -> 343068.75 | O45: =SUM(C45:N45) -> 1983600
A46: Revenue | C46: =C45*Scenario_Inputs!$B$7 -> 0 | D46: =D45*Scenario_Inputs!$B$7 -> 26718.75 | E46: =E45*Scenario_Inputs!$B$7 -> 58246.875 | F46: =F45*Scenario_Inputs!$B$7 -> 94584.375 | G46: =G45*Scenario_Inputs!$B$7 -> 109012.5 | H46: =H45*Scenario_Inputs!$B$7 -> 150159.38 | I46: =I45*Scenario_Inputs!$B$7 -> 169396.88 | J46: =J45*Scenario_Inputs!$B$7 -> 215353.12 | ... N46: =N45*Scenario_Inputs!$B$7 -> 343068.75 | O46: =SUM(C46:N46) -> 1983600
A47: Supplier cost | C47: =C45*(1-Assumptions!$B$6)*Scenario_Inputs!$C$7*(1+(1-Assumptions!$B$26)*Assumptions!$B$21*Assumptions!$B$27) -> 0 | D47: =D45*(1-Assumptions!$B$6)*Scenario_Inputs!$C$7*(1+(1-Assumptions!$B$26)*Assumptions!$B$21*Assumptions!$B$27) -> 19697.755 | E47: =E45*(1-Assumptions!$B$6)*Scenario_Inputs!$C$7*(1+(1-Assumptions!$B$26)*Assumptions!$B$21*Assumptions!$B$27) -> 42941.106 | F47: =F45*(1-Assumptions!$B$6)*Scenario_Inputs!$C$7*(1+(1-Assumptions!$B$26)*Assumptions!$B$21*Assumptions!$B$27) -> 69730.053 | G47: =G45*(1-Assumptions!$B$6)*Scenario_Inputs!$C$7*(1+(1-Assumptions!$B$26)*Assumptions!$B$21*Assumptions!$B$27) -> 80366.84 | H47: =H45*(1-Assumptions!$B$6)*Scenario_Inputs!$C$7*(1+(1-Assumptions!$B$26)*Assumptions!$B$21*Assumptions!$B$27) -> 110701.38 | I47: =I45*(1-Assumptions!$B$6)*Scenario_Inputs!$C$7*(1+(1-Assumptions!$B$26)*Assumptions!$B$21*Assumptions!$B$27) -> 124883.77 | J47: =J45*(1-Assumptions!$B$6)*Scenario_Inputs!$C$7*(1+(1-Assumptions!$B$26)*Assumptions!$B$21*Assumptions!$B$27) -> 158763.91 | ... N47: =N45*(1-Assumptions!$B$6)*Scenario_Inputs!$C$7*(1+(1-Assumptions!$B$26)*Assumptions!$B$21*Assumptions!$B$27) -> 252919.17 | O47: =SUM(C47:N47) -> 1462361.3
A48: Other variable (delivery/fees/rework) | C48: =C46*(Assumptions!$B$7+Assumptions!$B$8) -> 0 | D48: =D46*(Assumptions!$B$7+Assumptions!$B$8) -> 1603.125 | E48: =E46*(Assumptions!$B$7+Assumptions!$B$8) -> 3494.8125 | F48: =F46*(Assumptions!$B$7+Assumptions!$B$8) -> 5675.0625 | G48: =G46*(Assumptions!$B$7+Assumptions!$B$8) -> 6540.75 | H48: =H46*(Assumptions!$B$7+Assumptions!$B$8) -> 9009.5625 | I48: =I46*(Assumptions!$B$7+Assumptions!$B$8) -> 10163.812 | J48: =J46*(Assumptions!$B$7+Assumptions!$B$8) -> 12921.188 | ... N48: =N46*(Assumptions!$B$7+Assumptions!$B$8) -> 20584.125 | O48: =SUM(C48:N48) -> 119016
A49: Contribution | C49: =C46-C47-C48 -> 0 | D49: =D46-D47-D48 -> 5417.87 | E49: =E46-E47-E48 -> 11810.957 | F49: =F46-F47-F48 -> 19179.26 | G49: =G46-G47-G48 -> 22104.91 | H49: =H46-H47-H48 -> 30448.429 | I49: =I46-I47-I48 -> 34349.296 | J49: =J46-J47-J48 -> 43668.032 | ... N49: =N46-N47-N48 -> 69565.451 | O49: =SUM(C49:N49) -> 402222.67
A50: Fixed opex | C50: =Assumptions!$B$29 -> 32500 | D50: =Assumptions!$B$29 -> 32500 | E50: =Assumptions!$B$29 -> 32500 | F50: =Assumptions!$B$29 -> 32500 | G50: =Assumptions!$B$29 -> 32500 | H50: =Assumptions!$B$29 -> 32500 | I50: =Assumptions!$B$29 -> 32500 | J50: =Assumptions!$B$29 -> 32500 | ... N50: =Assumptions!$B$29 -> 32500 | O50: =SUM(C50:N50) -> 390000
A51: One-off costs | C51: =Scenario_Inputs!G$9 -> 0 | D51: =Scenario_Inputs!H$9 -> 0 | E51: =Scenario_Inputs!I$9 -> 0 | F51: =Scenario_Inputs!J$9 -> 0 | G51: =Scenario_Inputs!K$9 -> 0 | H51: =Scenario_Inputs!L$9 -> 0 | I51: =Scenario_Inputs!M$9 -> 0 | J51: =Scenario_Inputs!N$9 -> 0 | ... N51: =Scenario_Inputs!R$9 -> 0 | O51: =SUM(C51:N51) -> 0
A52: Operating profit BEFORE founder pay | C52: =C49-C50-C51 -> -32500 | D52: =D49-D50-D51 -> -27082.13 | E52: =E49-E50-E51 -> -20689.043 | F52: =F49-F50-F51 -> -13320.74 | G52: =G49-G50-G51 -> -10395.09 | H52: =H49-H50-H51 -> -2051.5706 | I52: =I49-I50-I51 -> 1849.2958 | J52: =J49-J50-J51 -> 11168.032 | ... N52: =N49-N50-N51 -> 37065.451 | O52: =SUM(C52:N52) -> 12222.669
A53: Founder compensation | C53: =IF(C40>=Assumptions!$B$13,Assumptions!$B$12,0) -> 0 | D53: =IF(D40>=Assumptions!$B$13,Assumptions!$B$12,0) -> 0 | E53: =IF(E40>=Assumptions!$B$13,Assumptions!$B$12,0) -> 0 | F53: =IF(F40>=Assumptions!$B$13,Assumptions!$B$12,0) -> 0 | G53: =IF(G40>=Assumptions!$B$13,Assumptions!$B$12,0) -> 0 | H53: =IF(H40>=Assumptions!$B$13,Assumptions!$B$12,0) -> 0 | I53: =IF(I40>=Assumptions!$B$13,Assumptions!$B$12,0) -> 15000 | J53: =IF(J40>=Assumptions!$B$13,Assumptions!$B$12,0) -> 15000 | ... N53: =IF(N40>=Assumptions!$B$13,Assumptions!$B$12,0) -> 15000 | O53: =SUM(C53:N53) -> 90000
A54: Operating profit AFTER founder pay | C54: =C52-C53 -> -32500 | D54: =D52-D53 -> -27082.13 | E54: =E52-E53 -> -20689.043 | F54: =F52-F53 -> -13320.74 | G54: =G52-G53 -> -10395.09 | H54: =H52-H53 -> -2051.5706 | I54: =I52-I53 -> -13150.704 | J54: =J52-J53 -> -3831.9678 | ... N54: =N52-N53 -> 22065.451 | O54: =SUM(C54:N54) -> -77777.331
A55: Cash receipts | C55: =Assumptions!$B$9*C46+(1-Assumptions!$B$9)*IF(C40-$Q$39>=1,INDEX($C46:$N46,C40-$Q$39),0) -> 0 | D55: =Assumptions!$B$9*D46+(1-Assumptions!$B$9)*IF(D40-$Q$39>=1,INDEX($C46:$N46,D40-$Q$39),0) -> 13359.375 | E55: =Assumptions!$B$9*E46+(1-Assumptions!$B$9)*IF(E40-$Q$39>=1,INDEX($C46:$N46,E40-$Q$39),0) -> 42482.812 | F55: =Assumptions!$B$9*F46+(1-Assumptions!$B$9)*IF(F40-$Q$39>=1,INDEX($C46:$N46,F40-$Q$39),0) -> 76415.625 | G55: =Assumptions!$B$9*G46+(1-Assumptions!$B$9)*IF(G40-$Q$39>=1,INDEX($C46:$N46,G40-$Q$39),0) -> 101798.44 | H55: =Assumptions!$B$9*H46+(1-Assumptions!$B$9)*IF(H40-$Q$39>=1,INDEX($C46:$N46,H40-$Q$39),0) -> 129585.94 | I55: =Assumptions!$B$9*I46+(1-Assumptions!$B$9)*IF(I40-$Q$39>=1,INDEX($C46:$N46,I40-$Q$39),0) -> 159778.12 | J55: =Assumptions!$B$9*J46+(1-Assumptions!$B$9)*IF(J40-$Q$39>=1,INDEX($C46:$N46,J40-$Q$39),0) -> 192375 | ... N55: =Assumptions!$B$9*N46+(1-Assumptions!$B$9)*IF(N40-$Q$39>=1,INDEX($C46:$N46,N40-$Q$39),0) -> 328640.62 | O55: =SUM(C55:N55) -> 1812065.6
A56: Cash payments | C56: =C47+C48+C50+C51+C53 -> 32500 | D56: =D47+D48+D50+D51+D53 -> 53800.88 | E56: =E47+E48+E50+E51+E53 -> 78935.918 | F56: =F47+F48+F50+F51+F53 -> 107905.12 | G56: =G47+G48+G50+G51+G53 -> 119407.59 | H56: =H47+H48+H50+H51+H53 -> 152210.95 | I56: =I47+I48+I50+I51+I53 -> 182547.58 | J56: =J47+J48+J50+J51+J53 -> 219185.09 | ... N56: =N47+N48+N50+N51+N53 -> 321003.3 | O56: =SUM(C56:N56) -> 2061377.3
A57: Net cash flow | C57: =C55-C56 -> -32500 | D57: =D55-D56 -> -40441.505 | E57: =E55-E56 -> -36453.106 | F57: =F55-F56 -> -31489.49 | G57: =G55-G56 -> -17609.153 | H57: =H55-H56 -> -22625.008 | I57: =I55-I56 -> -22769.454 | J57: =J55-J56 -> -26810.093 | ... N57: =N55-N56 -> 7637.3258 | O57: =SUM(C57:N57) -> -249311.71
A58: Closing cash | C58: =Capital_Allocation!$C$20+C57 -> 202500 | D58: =C58+D57 -> 162058.49 | E58: =D58+E57 -> 125605.39 | F58: =E58+F57 -> 94115.899 | G58: =F58+G57 -> 76506.746 | H58: =G58+H57 -> 53881.738 | I58: =H58+I57 -> 31112.284 | J58: =I58+J57 -> 4302.1909 | K58: =J58+K57 -> -6677.1314 | ... N58: =M58+N57 -> -14311.706
A59: Receivables balance | C59: =SUM($C46:C46)-SUM($C55:C55) -> 0 | D59: =SUM($C46:D46)-SUM($C55:D55) -> 13359.375 | E59: =SUM($C46:E46)-SUM($C55:E55) -> 29123.438 | F59: =SUM($C46:F46)-SUM($C55:F55) -> 47292.188 | G59: =SUM($C46:G46)-SUM($C55:G55) -> 54506.25 | H59: =SUM($C46:H46)-SUM($C55:H55) -> 75079.688 | I59: =SUM($C46:I46)-SUM($C55:I55) -> 84698.438 | J59: =SUM($C46:J46)-SUM($C55:J55) -> 107676.56 | ... N59: =SUM($C46:N46)-SUM($C55:N55) -> 171534.38
A60: Cumulative profit after founder | C60: =SUM($C54:C54) -> -32500 | D60: =SUM($C54:D54) -> -59582.13 | E60: =SUM($C54:E54) -> -80271.173 | F60: =SUM($C54:F54) -> -93591.914 | G60: =SUM($C54:G54) -> -103987 | H60: =SUM($C54:H54) -> -106038.57 | I60: =SUM($C54:I54) -> -119189.28 | J60: =SUM($C54:J54) -> -123021.25 | ... N60: =SUM($C54:N54) -> -77777.331
A61: Break-even flag (profit after founder >=0 -> month, else 99) | C61: =IF(C54>=0,C40,99) -> 99 | D61: =IF(D54>=0,D40,99) -> 99 | E61: =IF(E54>=0,E40,99) -> 99 | F61: =IF(F54>=0,F40,99) -> 99 | G61: =IF(G54>=0,G40,99) -> 99 | H61: =IF(H54>=0,H40,99) -> 99 | I61: =IF(I54>=0,I40,99) -> 99 | J61: =IF(J54>=0,J40,99) -> 99 | ... N61: =IF(N54>=0,N40,99) -> 12
A62: Break-even flag BEFORE founder (profit >=0 -> month, else 99) | C62: =IF(C52>=0,C40,99) -> 99 | D62: =IF(D52>=0,D40,99) -> 99 | E62: =IF(E52>=0,E40,99) -> 99 | F62: =IF(F52>=0,F40,99) -> 99 | G62: =IF(G52>=0,G40,99) -> 99 | H62: =IF(H52>=0,H40,99) -> 99 | I62: =IF(I52>=0,I40,99) -> 7 | J62: =IF(J52>=0,J40,99) -> 8 | ... N62: =IF(N52>=0,N40,99) -> 12
A63: Total revenue | B63: =O46 -> 1983600
A64: Total contribution | B64: =O49 -> 402222.67
A65: Total operating profit after founder | B65: =O54 -> -77777.331
A66: Minimum closing cash | B66: =MIN(C58:N58) -> -21949.032
A67: Ending cash (month 12) | B67: =N58 -> -14311.706
A68: Solvent within ceiling (cash never < 0)? | B68: =IF(B66>=0,"YES","NO") -> NO
A69: Solvent WITHOUT using contingency? | B69: =IF(B66>=Capital_Allocation!$C$16,"YES","NO") -> NO
A70: First month op. profit >= 0 BEFORE founder pay | B70: =IF(MIN(C62:N62)=99,"none in 12 mo",MIN(C62:N62)) -> 7
A71: Month-12 operating profit AFTER founder pay | B71: =N54 -> 22065.451
A72: Month-12 receivables | B72: =N59 -> 171534.38
A73: First month op. profit >= 0 AFTER founder pay | B73: =IF(MIN(C61:N61)=99,"none in 12 mo",MIN(C61:N61)) -> 9
A77: ENGINE: Upside | P77: Collection lag (months) | Q77: =MAX(1,ROUNDUP((Assumptions!$B$10+Scenario_Inputs!$F$11)/30,0)) -> 1
A78: Month | C78: 1 | D78: 2 | E78: 3 | F78: 4 | G78: 5 | H78: 6 | I78: 7 | J78: 8 | K78: 9 | L78: 10 | M78: 11 | N78: 12 | O78: 12-mo total
A79: New customers | C79: =Assumptions!B$33*Scenario_Inputs!$D$11 -> 0 | D79: =Assumptions!C$33*Scenario_Inputs!$D$11 -> 1.4 | E79: =Assumptions!D$33*Scenario_Inputs!$D$11 -> 2.8 | F79: =Assumptions!E$33*Scenario_Inputs!$D$11 -> 4.2 | G79: =Assumptions!F$33*Scenario_Inputs!$D$11 -> 4.2 | H79: =Assumptions!G$33*Scenario_Inputs!$D$11 -> 5.6 | I79: =Assumptions!H$33*Scenario_Inputs!$D$11 -> 5.6 | J79: =Assumptions!I$33*Scenario_Inputs!$D$11 -> 7 | ... N79: =Assumptions!M$33*Scenario_Inputs!$D$11 -> 8.4 | O79: =SUM(C79:N79) -> 61.6
A80: Customers at start of month | C80: 0 | D80: =SUM($C79:C79) -> 0 | E80: =SUM($C79:D79) -> 1.4 | F80: =SUM($C79:E79) -> 4.2 | G80: =SUM($C79:F79) -> 8.4 | H80: =SUM($C79:G79) -> 12.6 | I80: =SUM($C79:H79) -> 18.2 | J80: =SUM($C79:I79) -> 23.8 | K80: =SUM($C79:J79) -> 30.8 | ... N80: =SUM($C79:M79) -> 53.2
A81: Repeat orders | C81: =C80*Assumptions!$B$11*Scenario_Inputs!$E$11 -> 0 | D81: =D80*Assumptions!$B$11*Scenario_Inputs!$E$11 -> 0 | E81: =E80*Assumptions!$B$11*Scenario_Inputs!$E$11 -> 0.3276 | F81: =F80*Assumptions!$B$11*Scenario_Inputs!$E$11 -> 0.9828 | G81: =G80*Assumptions!$B$11*Scenario_Inputs!$E$11 -> 1.9656 | H81: =H80*Assumptions!$B$11*Scenario_Inputs!$E$11 -> 2.9484 | I81: =I80*Assumptions!$B$11*Scenario_Inputs!$E$11 -> 4.2588 | J81: =J80*Assumptions!$B$11*Scenario_Inputs!$E$11 -> 5.5692 | ... N81: =N80*Assumptions!$B$11*Scenario_Inputs!$E$11 -> 12.4488 | O81: =SUM(C81:N81) -> 55.0368
A82: Total orders | C82: =C79+C81 -> 0 | D82: =D79+D81 -> 1.4 | E82: =E79+E81 -> 3.1276 | F82: =F79+F81 -> 5.1828 | G82: =G79+G81 -> 6.1656 | H82: =H79+H81 -> 8.5484 | I82: =I79+I81 -> 9.8588 | J82: =J79+J81 -> 12.5692 | ... N82: =N79+N81 -> 20.8488 | O82: =SUM(C82:N82) -> 116.6368
A83: Base revenue (pre price shock) | C83: =C82*Assumptions!$B$5*Scenario_Inputs!G$12 -> 0 | D83: =D82*Assumptions!$B$5*Scenario_Inputs!H$12 -> 37406.25 | E83: =E82*Assumptions!$B$5*Scenario_Inputs!I$12 -> 83565.562 | F83: =F82*Assumptions!$B$5*Scenario_Inputs!J$12 -> 138477.94 | G83: =G82*Assumptions!$B$5*Scenario_Inputs!K$12 -> 164737.12 | H83: =H82*Assumptions!$B$5*Scenario_Inputs!L$12 -> 228402.56 | I83: =I82*Assumptions!$B$5*Scenario_Inputs!M$12 -> 263414.81 | J83: =J82*Assumptions!$B$5*Scenario_Inputs!N$12 -> 335833.31 | ... N83: =N82*Assumptions!$B$5*Scenario_Inputs!R$12 -> 557053.88 | O83: =SUM(C83:N83) -> 3116389.5
A84: Revenue | C84: =C83*Scenario_Inputs!$B$11 -> 0 | D84: =D83*Scenario_Inputs!$B$11 -> 37406.25 | E84: =E83*Scenario_Inputs!$B$11 -> 83565.562 | F84: =F83*Scenario_Inputs!$B$11 -> 138477.94 | G84: =G83*Scenario_Inputs!$B$11 -> 164737.12 | H84: =H83*Scenario_Inputs!$B$11 -> 228402.56 | I84: =I83*Scenario_Inputs!$B$11 -> 263414.81 | J84: =J83*Scenario_Inputs!$B$11 -> 335833.31 | ... N84: =N83*Scenario_Inputs!$B$11 -> 557053.88 | O84: =SUM(C84:N84) -> 3116389.5
A85: Supplier cost | C85: =C83*(1-Assumptions!$B$6)*Scenario_Inputs!$C$11*(1+(1-Assumptions!$B$26)*Assumptions!$B$21*Assumptions!$B$27) -> 0 | D85: =D83*(1-Assumptions!$B$6)*Scenario_Inputs!$C$11*(1+(1-Assumptions!$B$26)*Assumptions!$B$21*Assumptions!$B$27) -> 26749.551 | E85: =E83*(1-Assumptions!$B$6)*Scenario_Inputs!$C$11*(1+(1-Assumptions!$B$26)*Assumptions!$B$21*Assumptions!$B$27) -> 59758.498 | F85: =F83*(1-Assumptions!$B$6)*Scenario_Inputs!$C$11*(1+(1-Assumptions!$B$26)*Assumptions!$B$21*Assumptions!$B$27) -> 99026.839 | G85: =G83*(1-Assumptions!$B$6)*Scenario_Inputs!$C$11*(1+(1-Assumptions!$B$26)*Assumptions!$B$21*Assumptions!$B$27) -> 117805.02 | H85: =H83*(1-Assumptions!$B$6)*Scenario_Inputs!$C$11*(1+(1-Assumptions!$B$26)*Assumptions!$B$21*Assumptions!$B$27) -> 163332.76 | I85: =I83*(1-Assumptions!$B$6)*Scenario_Inputs!$C$11*(1+(1-Assumptions!$B$26)*Assumptions!$B$21*Assumptions!$B$27) -> 188370.34 | J85: =J83*(1-Assumptions!$B$6)*Scenario_Inputs!$C$11*(1+(1-Assumptions!$B$26)*Assumptions!$B$21*Assumptions!$B$27) -> 240157.47 | ... N85: =N83*(1-Assumptions!$B$6)*Scenario_Inputs!$C$11*(1+(1-Assumptions!$B$26)*Assumptions!$B$21*Assumptions!$B$27) -> 398354.32 | O85: =SUM(C85:N85) -> 2228558.6
A86: Other variable (delivery/fees/rework) | C86: =C84*(Assumptions!$B$7+Assumptions!$B$8) -> 0 | D86: =D84*(Assumptions!$B$7+Assumptions!$B$8) -> 2244.375 | E86: =E84*(Assumptions!$B$7+Assumptions!$B$8) -> 5013.9338 | F86: =F84*(Assumptions!$B$7+Assumptions!$B$8) -> 8308.6763 | G86: =G84*(Assumptions!$B$7+Assumptions!$B$8) -> 9884.2275 | H86: =H84*(Assumptions!$B$7+Assumptions!$B$8) -> 13704.154 | I86: =I84*(Assumptions!$B$7+Assumptions!$B$8) -> 15804.889 | J86: =J84*(Assumptions!$B$7+Assumptions!$B$8) -> 20149.999 | ... N86: =N84*(Assumptions!$B$7+Assumptions!$B$8) -> 33423.232 | O86: =SUM(C86:N86) -> 186983.37
A87: Contribution | C87: =C84-C85-C86 -> 0 | D87: =D84-D85-D86 -> 8412.3237 | E87: =E84-E85-E86 -> 18793.131 | F87: =F84-F85-F86 -> 31142.422 | G87: =G84-G85-G86 -> 37047.874 | H87: =H84-H85-H86 -> 51365.649 | I87: =I84-I85-I86 -> 59239.584 | J87: =J84-J85-J86 -> 75525.842 | ... N87: =N84-N85-N86 -> 125276.32 | O87: =SUM(C87:N87) -> 700847.51
A88: Fixed opex | C88: =Assumptions!$B$29 -> 32500 | D88: =Assumptions!$B$29 -> 32500 | E88: =Assumptions!$B$29 -> 32500 | F88: =Assumptions!$B$29 -> 32500 | G88: =Assumptions!$B$29 -> 32500 | H88: =Assumptions!$B$29 -> 32500 | I88: =Assumptions!$B$29 -> 32500 | J88: =Assumptions!$B$29 -> 32500 | ... N88: =Assumptions!$B$29 -> 32500 | O88: =SUM(C88:N88) -> 390000
A89: One-off costs | C89: =Scenario_Inputs!G$13 -> 0 | D89: =Scenario_Inputs!H$13 -> 0 | E89: =Scenario_Inputs!I$13 -> 0 | F89: =Scenario_Inputs!J$13 -> 0 | G89: =Scenario_Inputs!K$13 -> 0 | H89: =Scenario_Inputs!L$13 -> 0 | I89: =Scenario_Inputs!M$13 -> 0 | J89: =Scenario_Inputs!N$13 -> 0 | ... N89: =Scenario_Inputs!R$13 -> 0 | O89: =SUM(C89:N89) -> 0
A90: Operating profit BEFORE founder pay | C90: =C87-C88-C89 -> -32500 | D90: =D87-D88-D89 -> -24087.676 | E90: =E87-E88-E89 -> -13706.869 | F90: =F87-F88-F89 -> -1357.5776 | G90: =G87-G88-G89 -> 4547.8736 | H90: =H87-H88-H89 -> 18865.649 | I90: =I87-I88-I89 -> 26739.584 | J90: =J87-J88-J89 -> 43025.842 | ... N90: =N87-N88-N89 -> 92776.325 | O90: =SUM(C90:N90) -> 310847.51
A91: Founder compensation | C91: =IF(C78>=Assumptions!$B$13,Assumptions!$B$12,0) -> 0 | D91: =IF(D78>=Assumptions!$B$13,Assumptions!$B$12,0) -> 0 | E91: =IF(E78>=Assumptions!$B$13,Assumptions!$B$12,0) -> 0 | F91: =IF(F78>=Assumptions!$B$13,Assumptions!$B$12,0) -> 0 | G91: =IF(G78>=Assumptions!$B$13,Assumptions!$B$12,0) -> 0 | H91: =IF(H78>=Assumptions!$B$13,Assumptions!$B$12,0) -> 0 | I91: =IF(I78>=Assumptions!$B$13,Assumptions!$B$12,0) -> 15000 | J91: =IF(J78>=Assumptions!$B$13,Assumptions!$B$12,0) -> 15000 | ... N91: =IF(N78>=Assumptions!$B$13,Assumptions!$B$12,0) -> 15000 | O91: =SUM(C91:N91) -> 90000
A92: Operating profit AFTER founder pay | C92: =C90-C91 -> -32500 | D92: =D90-D91 -> -24087.676 | E92: =E90-E91 -> -13706.869 | F92: =F90-F91 -> -1357.5776 | G92: =G90-G91 -> 4547.8736 | H92: =H90-H91 -> 18865.649 | I92: =I90-I91 -> 11739.584 | J92: =J90-J91 -> 28025.842 | ... N92: =N90-N91 -> 77776.325 | O92: =SUM(C92:N92) -> 220847.51
A93: Cash receipts | C93: =Assumptions!$B$9*C84+(1-Assumptions!$B$9)*IF(C78-$Q$77>=1,INDEX($C84:$N84,C78-$Q$77),0) -> 0 | D93: =Assumptions!$B$9*D84+(1-Assumptions!$B$9)*IF(D78-$Q$77>=1,INDEX($C84:$N84,D78-$Q$77),0) -> 18703.125 | E93: =Assumptions!$B$9*E84+(1-Assumptions!$B$9)*IF(E78-$Q$77>=1,INDEX($C84:$N84,E78-$Q$77),0) -> 60485.906 | F93: =Assumptions!$B$9*F84+(1-Assumptions!$B$9)*IF(F78-$Q$77>=1,INDEX($C84:$N84,F78-$Q$77),0) -> 111021.75 | G93: =Assumptions!$B$9*G84+(1-Assumptions!$B$9)*IF(G78-$Q$77>=1,INDEX($C84:$N84,G78-$Q$77),0) -> 151607.53 | H93: =Assumptions!$B$9*H84+(1-Assumptions!$B$9)*IF(H78-$Q$77>=1,INDEX($C84:$N84,H78-$Q$77),0) -> 196569.84 | I93: =Assumptions!$B$9*I84+(1-Assumptions!$B$9)*IF(I78-$Q$77>=1,INDEX($C84:$N84,I78-$Q$77),0) -> 245908.69 | J93: =Assumptions!$B$9*J84+(1-Assumptions!$B$9)*IF(J78-$Q$77>=1,INDEX($C84:$N84,J78-$Q$77),0) -> 299624.06 | ... N93: =Assumptions!$B$9*N84+(1-Assumptions!$B$9)*IF(N78-$Q$77>=1,INDEX($C84:$N84,N78-$Q$77),0) -> 530794.69 | O93: =SUM(C93:N93) -> 2837862.6
A94: Cash payments | C94: =C85+C86+C88+C89+C91 -> 32500 | D94: =D85+D86+D88+D89+D91 -> 61493.926 | E94: =E85+E86+E88+E89+E91 -> 97272.431 | F94: =F85+F86+F88+F89+F91 -> 139835.52 | G94: =G85+G86+G88+G89+G91 -> 160189.25 | H94: =H85+H86+H88+H89+H91 -> 209536.91 | I94: =I85+I86+I88+I89+I91 -> 251675.23 | J94: =J85+J86+J88+J89+J91 -> 307807.47 | ... N94: =N85+N86+N88+N89+N91 -> 479277.55 | O94: =SUM(C94:N94) -> 2895542
A95: Net cash flow | C95: =C93-C94 -> -32500 | D95: =D93-D94 -> -42790.801 | E95: =E93-E94 -> -36786.525 | F95: =F93-F94 -> -28813.765 | G95: =G93-G94 -> -8581.7201 | H95: =H93-H94 -> -12967.07 | I95: =I93-I94 -> -5766.5414 | J95: =J93-J94 -> -8183.4077 | ... N95: =N93-N94 -> 51517.137 | O95: =SUM(C95:N95) -> -57679.425
A96: Closing cash | C96: =Capital_Allocation!$C$20+C95 -> 202500 | D96: =C96+D95 -> 159709.2 | E96: =D96+E95 -> 122922.67 | F96: =E96+F95 -> 94108.909 | G96: =F96+G95 -> 85527.188 | H96: =G96+H95 -> 72560.118 | I96: =H96+I95 -> 66793.577 | J96: =I96+J95 -> 58610.169 | K96: =J96+K95 -> 74595.774 | ... N96: =M96+N95 -> 177320.58
A97: Receivables balance | C97: =SUM($C84:C84)-SUM($C93:C93) -> 0 | D97: =SUM($C84:D84)-SUM($C93:D93) -> 18703.125 | E97: =SUM($C84:E84)-SUM($C93:E93) -> 41782.781 | F97: =SUM($C84:F84)-SUM($C93:F93) -> 69238.969 | G97: =SUM($C84:G84)-SUM($C93:G93) -> 82368.562 | H97: =SUM($C84:H84)-SUM($C93:H93) -> 114201.28 | I97: =SUM($C84:I84)-SUM($C93:I93) -> 131707.41 | J97: =SUM($C84:J84)-SUM($C93:J93) -> 167916.66 | ... N97: =SUM($C84:N84)-SUM($C93:N93) -> 278526.94
A98: Cumulative profit after founder | C98: =SUM($C92:C92) -> -32500 | D98: =SUM($C92:D92) -> -56587.676 | E98: =SUM($C92:E92) -> -70294.545 | F98: =SUM($C92:F92) -> -71652.123 | G98: =SUM($C92:G92) -> -67104.249 | H98: =SUM($C92:H92) -> -48238.601 | I98: =SUM($C92:I92) -> -36499.017 | J98: =SUM($C92:J92) -> -8473.1747 | ... N98: =SUM($C92:N92) -> 220847.51
A99: Break-even flag (profit after founder >=0 -> month, else 99) | C99: =IF(C92>=0,C78,99) -> 99 | D99: =IF(D92>=0,D78,99) -> 99 | E99: =IF(E92>=0,E78,99) -> 99 | F99: =IF(F92>=0,F78,99) -> 99 | G99: =IF(G92>=0,G78,99) -> 5 | H99: =IF(H92>=0,H78,99) -> 6 | I99: =IF(I92>=0,I78,99) -> 7 | J99: =IF(J92>=0,J78,99) -> 8 | ... N99: =IF(N92>=0,N78,99) -> 12
A100: Break-even flag BEFORE founder (profit >=0 -> month, else 99) | C100: =IF(C90>=0,C78,99) -> 99 | D100: =IF(D90>=0,D78,99) -> 99 | E100: =IF(E90>=0,E78,99) -> 99 | F100: =IF(F90>=0,F78,99) -> 99 | G100: =IF(G90>=0,G78,99) -> 5 | H100: =IF(H90>=0,H78,99) -> 6 | I100: =IF(I90>=0,I78,99) -> 7 | J100: =IF(J90>=0,J78,99) -> 8 | ... N100: =IF(N90>=0,N78,99) -> 12
A101: Total revenue | B101: =O84 -> 3116389.5
A102: Total contribution | B102: =O87 -> 700847.51
A103: Total operating profit after founder | B103: =O92 -> 220847.51
A104: Minimum closing cash | B104: =MIN(C96:N96) -> 58610.169
A105: Ending cash (month 12) | B105: =N96 -> 177320.58
A106: Solvent within ceiling (cash never < 0)? | B106: =IF(B104>=0,"YES","NO") -> YES
...

Sheet Revenue_Forecast
A1: NPR (Base case) | B1: M1 | C1: M2 | D1: M3 | E1: M4 | F1: M5 | G1: M6 | H1: M7 | I1: M8 | J1: M9 | K1: M10 | L1: M11 | M1: M12 | N1: 12-mo
A2: New customers | B2: =Engine!C41 -> 0 | C2: =Engine!D41 -> 1 | D2: =Engine!E41 -> 2 | E2: =Engine!F41 -> 3 | F2: =Engine!G41 -> 3 | G2: =Engine!H41 -> 4 | H2: =Engine!I41 -> 4 | I2: =Engine!J41 -> 5 | ... M2: =Engine!N41 -> 6 | N2: =SUM(B2:M2) -> 44
A3: Customers at start of month | B3: =Engine!C42 -> 0 | C3: =Engine!D42 -> 0 | D3: =Engine!E42 -> 1 | E3: =Engine!F42 -> 3 | F3: =Engine!G42 -> 6 | G3: =Engine!H42 -> 9 | H3: =Engine!I42 -> 13 | I3: =Engine!J42 -> 17 | ... M3: =Engine!N42 -> 38
A4: Repeat orders | B4: =Engine!C43 -> 0 | C4: =Engine!D43 -> 0 | D4: =Engine!E43 -> 0.18 | E4: =Engine!F43 -> 0.54 | F4: =Engine!G43 -> 1.08 | G4: =Engine!H43 -> 1.62 | H4: =Engine!I43 -> 2.34 | I4: =Engine!J43 -> 3.06 | ... M4: =Engine!N43 -> 6.84 | N4: =SUM(B4:M4) -> 30.24
A5: Total orders | B5: =Engine!C44 -> 0 | C5: =Engine!D44 -> 1 | D5: =Engine!E44 -> 2.18 | E5: =Engine!F44 -> 3.54 | F5: =Engine!G44 -> 4.08 | G5: =Engine!H44 -> 5.62 | H5: =Engine!I44 -> 6.34 | I5: =Engine!J44 -> 8.06 | ... M5: =Engine!N44 -> 12.84 | N5: =SUM(B5:M5) -> 74.24
A6: Revenue (ex-VAT) | B6: =Engine!C46 -> 0 | C6: =Engine!D46 -> 26718.75 | D6: =Engine!E46 -> 58246.875 | E6: =Engine!F46 -> 94584.375 | F6: =Engine!G46 -> 109012.5 | G6: =Engine!H46 -> 150159.38 | H6: =Engine!I46 -> 169396.88 | I6: =Engine!J46 -> 215353.12 | ... M6: =Engine!N46 -> 343068.75 | N6: =SUM(B6:M6) -> 1983600

Sheet Monthly_Sales_Assumptions
A1: NPR (Base case) | B1: M1 | C1: M2 | D1: M3 | E1: M4 | F1: M5 | G1: M6 | H1: M7 | I1: M8 | J1: M9 | K1: M10 | L1: M11 | M1: M12 | N1: 12-mo
A2: New customers (Assumptions x acquisition multiplier) | B2: =Engine!C41 -> 0 | C2: =Engine!D41 -> 1 | D2: =Engine!E41 -> 2 | E2: =Engine!F41 -> 3 | F2: =Engine!G41 -> 3 | G2: =Engine!H41 -> 4 | H2: =Engine!I41 -> 4 | I2: =Engine!J41 -> 5 | ... M2: =Engine!N41 -> 6 | N2: =SUM(B2:M2) -> 44
A3: Reorder probability applied -> repeat orders | B3: =Engine!C43 -> 0 | C3: =Engine!D43 -> 0 | D3: =Engine!E43 -> 0.18 | E3: =Engine!F43 -> 0.54 | F3: =Engine!G43 -> 1.08 | G3: =Engine!H43 -> 1.62 | H3: =Engine!I43 -> 2.34 | I3: =Engine!J43 -> 3.06 | ... M3: =Engine!N43 -> 6.84 | N3: =SUM(B3:M3) -> 30.24
A4: Total orders | B4: =Engine!C44 -> 0 | C4: =Engine!D44 -> 1 | D4: =Engine!E44 -> 2.18 | E4: =Engine!F44 -> 3.54 | F4: =Engine!G44 -> 4.08 | G4: =Engine!H44 -> 5.62 | H4: =Engine!I44 -> 6.34 | I4: =Engine!J44 -> 8.06 | ... M4: =Engine!N44 -> 12.84 | N4: =SUM(B4:M4) -> 74.24

Sheet Opex
A1: NPR (Base case) | B1: M1 | C1: M2 | D1: M3 | E1: M4 | F1: M5 | G1: M6 | H1: M7 | I1: M8 | J1: M9 | K1: M10 | L1: M11 | M1: M12 | N1: 12-mo
A2: Fixed opex | B2: =Engine!C50 -> 32500 | C2: =Engine!D50 -> 32500 | D2: =Engine!E50 -> 32500 | E2: =Engine!F50 -> 32500 | F2: =Engine!G50 -> 32500 | G2: =Engine!H50 -> 32500 | H2: =Engine!I50 -> 32500 | I2: =Engine!J50 -> 32500 | ... M2: =Engine!N50 -> 32500 | N2: =SUM(B2:M2) -> 390000
A3: One-off costs | B3: =Engine!C51 -> 0 | C3: =Engine!D51 -> 0 | D3: =Engine!E51 -> 0 | E3: =Engine!F51 -> 0 | F3: =Engine!G51 -> 0 | G3: =Engine!H51 -> 0 | H3: =Engine!I51 -> 0 | I3: =Engine!J51 -> 0 | ... M3: =Engine!N51 -> 0 | N3: =SUM(B3:M3) -> 0
A4: Founder compensation | B4: =Engine!C53 -> 0 | C4: =Engine!D53 -> 0 | D4: =Engine!E53 -> 0 | E4: =Engine!F53 -> 0 | F4: =Engine!G53 -> 0 | G4: =Engine!H53 -> 0 | H4: =Engine!I53 -> 15000 | I4: =Engine!J53 -> 15000 | ... M4: =Engine!N53 -> 15000 | N4: =SUM(B4:M4) -> 90000

Sheet Profit_and_Loss
A1: NPR (Base case) | B1: M1 | C1: M2 | D1: M3 | E1: M4 | F1: M5 | G1: M6 | H1: M7 | I1: M8 | J1: M9 | K1: M10 | L1: M11 | M1: M12 | N1: 12-mo
A2: Revenue | B2: =Engine!C46 -> 0 | C2: =Engine!D46 -> 26718.75 | D2: =Engine!E46 -> 58246.875 | E2: =Engine!F46 -> 94584.375 | F2: =Engine!G46 -> 109012.5 | G2: =Engine!H46 -> 150159.38 | H2: =Engine!I46 -> 169396.88 | I2: =Engine!J46 -> 215353.12 | ... M2: =Engine!N46 -> 343068.75 | N2: =SUM(B2:M2) -> 1983600
A3: Supplier cost (outsourced production, incl. unrecoverable VAT if unregistered) | B3: =Engine!C47 -> 0 | C3: =Engine!D47 -> 19697.755 | D3: =Engine!E47 -> 42941.106 | E3: =Engine!F47 -> 69730.053 | F3: =Engine!G47 -> 80366.84 | G3: =Engine!H47 -> 110701.38 | H3: =Engine!I47 -> 124883.77 | I3: =Engine!J47 -> 158763.91 | ... M3: =Engine!N47 -> 252919.17 | N3: =SUM(B3:M3) -> 1462361.3
A4: Other variable (delivery, fees, rework) | B4: =Engine!C48 -> 0 | C4: =Engine!D48 -> 1603.125 | D4: =Engine!E48 -> 3494.8125 | E4: =Engine!F48 -> 5675.0625 | F4: =Engine!G48 -> 6540.75 | G4: =Engine!H48 -> 9009.5625 | H4: =Engine!I48 -> 10163.812 | I4: =Engine!J48 -> 12921.188 | ... M4: =Engine!N48 -> 20584.125 | N4: =SUM(B4:M4) -> 119016
A5: Contribution | B5: =Engine!C49 -> 0 | C5: =Engine!D49 -> 5417.87 | D5: =Engine!E49 -> 11810.957 | E5: =Engine!F49 -> 19179.26 | F5: =Engine!G49 -> 22104.91 | G5: =Engine!H49 -> 30448.429 | H5: =Engine!I49 -> 34349.296 | I5: =Engine!J49 -> 43668.032 | ... M5: =Engine!N49 -> 69565.451 | N5: =SUM(B5:M5) -> 402222.67
A6: Fixed opex | B6: =Engine!C50 -> 32500 | C6: =Engine!D50 -> 32500 | D6: =Engine!E50 -> 32500 | E6: =Engine!F50 -> 32500 | F6: =Engine!G50 -> 32500 | G6: =Engine!H50 -> 32500 | H6: =Engine!I50 -> 32500 | I6: =Engine!J50 -> 32500 | ... M6: =Engine!N50 -> 32500 | N6: =SUM(B6:M6) -> 390000
A7: One-off costs | B7: =Engine!C51 -> 0 | C7: =Engine!D51 -> 0 | D7: =Engine!E51 -> 0 | E7: =Engine!F51 -> 0 | F7: =Engine!G51 -> 0 | G7: =Engine!H51 -> 0 | H7: =Engine!I51 -> 0 | I7: =Engine!J51 -> 0 | ... M7: =Engine!N51 -> 0 | N7: =SUM(B7:M7) -> 0
A8: Operating profit before founder pay | B8: =Engine!C52 -> -32500 | C8: =Engine!D52 -> -27082.13 | D8: =Engine!E52 -> -20689.043 | E8: =Engine!F52 -> -13320.74 | F8: =Engine!G52 -> -10395.09 | G8: =Engine!H52 -> -2051.5706 | H8: =Engine!I52 -> 1849.2958 | I8: =Engine!J52 -> 11168.032 | ... M8: =Engine!N52 -> 37065.451 | N8: =SUM(B8:M8) -> 12222.669
A9: Founder compensation | B9: =Engine!C53 -> 0 | C9: =Engine!D53 -> 0 | D9: =Engine!E53 -> 0 | E9: =Engine!F53 -> 0 | F9: =Engine!G53 -> 0 | G9: =Engine!H53 -> 0 | H9: =Engine!I53 -> 15000 | I9: =Engine!J53 -> 15000 | ... M9: =Engine!N53 -> 15000 | N9: =SUM(B9:M9) -> 90000
A10: Operating profit after founder pay (net profit proxy, pre-tax) | B10: =Engine!C54 -> -32500 | C10: =Engine!D54 -> -27082.13 | D10: =Engine!E54 -> -20689.043 | E10: =Engine!F54 -> -13320.74 | F10: =Engine!G54 -> -10395.09 | G10: =Engine!H54 -> -2051.5706 | H10: =Engine!I54 -> -13150.704 | I10: =Engine!J54 -> -3831.9678 | ... M10: =Engine!N54 -> 22065.451 | N10: =SUM(B10:M10) -> -77777.331
A11: Cumulative profit after founder | B11: =Engine!C60 -> -32500 | C11: =Engine!D60 -> -59582.13 | D11: =Engine!E60 -> -80271.173 | E11: =Engine!F60 -> -93591.914 | F11: =Engine!G60 -> -103987 | G11: =Engine!H60 -> -106038.57 | H11: =Engine!I60 -> -119189.28 | I11: =Engine!J60 -> -123021.25 | ... M11: =Engine!N60 -> -77777.331

Sheet Cash_Flow
A1: NPR (Base case) | B1: M1 | C1: M2 | D1: M3 | E1: M4 | F1: M5 | G1: M6 | H1: M7 | I1: M8 | J1: M9 | K1: M10 | L1: M11 | M1: M12 | N1: 12-mo
A2: Cash receipts (deposit + collections) | B2: =Engine!C55 -> 0 | C2: =Engine!D55 -> 13359.375 | D2: =Engine!E55 -> 42482.812 | E2: =Engine!F55 -> 76415.625 | F2: =Engine!G55 -> 101798.44 | G2: =Engine!H55 -> 129585.94 | H2: =Engine!I55 -> 159778.12 | I2: =Engine!J55 -> 192375 | ... M2: =Engine!N55 -> 328640.62 | N2: =SUM(B2:M2) -> 1812065.6
A3: Cash payments | B3: =Engine!C56 -> 32500 | C3: =Engine!D56 -> 53800.88 | D3: =Engine!E56 -> 78935.918 | E3: =Engine!F56 -> 107905.12 | F3: =Engine!G56 -> 119407.59 | G3: =Engine!H56 -> 152210.95 | H3: =Engine!I56 -> 182547.58 | I3: =Engine!J56 -> 219185.09 | ... M3: =Engine!N56 -> 321003.3 | N3: =SUM(B3:M3) -> 2061377.3
A4: Net cash flow | B4: =Engine!C57 -> -32500 | C4: =Engine!D57 -> -40441.505 | D4: =Engine!E57 -> -36453.106 | E4: =Engine!F57 -> -31489.49 | F4: =Engine!G57 -> -17609.153 | G4: =Engine!H57 -> -22625.008 | H4: =Engine!I57 -> -22769.454 | I4: =Engine!J57 -> -26810.093 | ... M4: =Engine!N57 -> 7637.3258 | N4: =SUM(B4:M4) -> -249311.71
A5: Closing cash (opening = WC + contingency) | B5: =Engine!C58 -> 202500 | C5: =Engine!D58 -> 162058.49 | D5: =Engine!E58 -> 125605.39 | E5: =Engine!F58 -> 94115.899 | F5: =Engine!G58 -> 76506.746 | G5: =Engine!H58 -> 53881.738 | H5: =Engine!I58 -> 31112.284 | I5: =Engine!J58 -> 4302.1909 | ... M5: =Engine!N58 -> -14311.706

Sheet Working_Capital
A1: NPR (Base case) | B1: M1 | C1: M2 | D1: M3 | E1: M4 | F1: M5 | G1: M6 | H1: M7 | I1: M8 | J1: M9 | K1: M10 | L1: M11 | M1: M12 | N1: 12-mo
A2: Revenue billed | B2: =Engine!C46 -> 0 | C2: =Engine!D46 -> 26718.75 | D2: =Engine!E46 -> 58246.875 | E2: =Engine!F46 -> 94584.375 | F2: =Engine!G46 -> 109012.5 | G2: =Engine!H46 -> 150159.38 | H2: =Engine!I46 -> 169396.88 | I2: =Engine!J46 -> 215353.12 | ... M2: =Engine!N46 -> 343068.75 | N2: =SUM(B2:M2) -> 1983600
A3: Cash receipts | B3: =Engine!C55 -> 0 | C3: =Engine!D55 -> 13359.375 | D3: =Engine!E55 -> 42482.812 | E3: =Engine!F55 -> 76415.625 | F3: =Engine!G55 -> 101798.44 | G3: =Engine!H55 -> 129585.94 | H3: =Engine!I55 -> 159778.12 | I3: =Engine!J55 -> 192375 | ... M3: =Engine!N55 -> 328640.62 | N3: =SUM(B3:M3) -> 1812065.6
A4: Receivables balance | B4: =Engine!C59 -> 0 | C4: =Engine!D59 -> 13359.375 | D4: =Engine!E59 -> 29123.438 | E4: =Engine!F59 -> 47292.188 | F4: =Engine!G59 -> 54506.25 | G4: =Engine!H59 -> 75079.688 | H4: =Engine!I59 -> 84698.438 | I4: =Engine!J59 -> 107676.56 | ... M4: =Engine!N59 -> 171534.38
A5: Closing cash | B5: =Engine!C58 -> 202500 | C5: =Engine!D58 -> 162058.49 | D5: =Engine!E58 -> 125605.39 | E5: =Engine!F58 -> 94115.899 | F5: =Engine!G58 -> 76506.746 | G5: =Engine!H58 -> 53881.738 | H5: =Engine!I58 -> 31112.284 | I5: =Engine!J58 -> 4302.1909 | ... M5: =Engine!N58 -> -14311.706
A8: Profit is not cash: receivables grow as customers pay balances 30+ days late; supplier cost is paid at order. Opening cash = working-capital reserve + contingency from Capital_Allocation.

Sheet Break_Even
A1: Metric | B1: Value | C1: Formula / note
A2: Contribution margin ratio | B2: =(1-(1-Assumptions!$B$6)*(1+(1-Assumptions!$B$26)*Assumptions!$B$21*Assumptions!$B$27)-Assumptions!$B$7-Assumptions!$B$8) -> 0.20277408 | C2: 1 - supplier cost x VAT leakage - variable selling/delivery - rework (v2 audit fix)
A3: Fixed opex per month (excl. founder) | B3: =Assumptions!$B$29 -> 32500
A4: Break-even monthly sales (excl. founder pay) | B4: =B3/B2 -> 160276.89 | C4: fixed / CM ratio
A5: Break-even monthly sales (incl. founder pay) | B5: =(B3+Assumptions!$B$12)/B2 -> 234250.84 | C5: covers founder compensation
A6: Orders per month to break even (excl. founder) | B6: =B4/Assumptions!$B$5 -> 5.9986674
A7: Orders per month to break even (incl. founder) | B7: =B5/Assumptions!$B$5 -> 8.7672831
A8: Contribution per average order | B8: =Assumptions!$B$5*B2 -> 5417.87
A9: Active customers needed if only reorders (no new) | B9: =B7/Assumptions!$B$11 -> 48.707128 | C9: orders needed / monthly reorder probability
A10: Average monthly revenue per active customer | B10: =Assumptions!$B$5*Assumptions!$B$11 -> 4809.375 | C10: AOV x reorder probability
A11: Set-up spend to recover (recommended config) | B11: =Capital_Allocation!$C$14 -> 265000 | C11: non-cash-reserve spend
A12: Month-12 operating profit after founder (Base) | B12: =Engine!$B$71 -> 22065.451
A13: Months to recover set-up spend at M12 run-rate | B13: =IF(B12>0,B11/B12,"not recovered at M12 run-rate") -> 12.009725 | C13: simple payback on run-rate; Base case
A14: Operating break-even month BEFORE founder (Base) | B14: =Engine!$B$70 -> 7
A15: Operating break-even month AFTER founder (Base) | B15: =Engine!$B$73 -> 9
A16: Orders per month in Base month 12 | B16: =Engine!N44 -> 12.84

Sheet Scenario_Analysis
A1: Scenario | B1: 12-mo revenue | C1: 12-mo contribution | D1: 12-mo op. profit after founder | E1: Minimum cash | F1: Ending cash | G1: Solvent within NPR 5L? | H1: Solvent without contingency? | I1: First profit month (before founder)
A2: Downside | B2: =Engine!$B$25 -> 830205 | C2: =Engine!$B$26 -> 107139.19 | D2: =Engine!$B$27 -> -372860.81 | E2: =Engine!$B$28 -> -268515.5 | F2: =Engine!$B$29 -> -268515.5 | G2: =Engine!$B$30 -> NO | H2: =Engine!$B$31 -> NO | I2: =Engine!$B$32 -> none in 12 mo
A3: Base | B3: =Engine!$B$63 -> 1983600 | C3: =Engine!$B$64 -> 402222.67 | D3: =Engine!$B$65 -> -77777.331 | E3: =Engine!$B$66 -> -21949.032 | F3: =Engine!$B$67 -> -14311.706 | G3: =Engine!$B$68 -> NO | H3: =Engine!$B$69 -> NO | I3: =Engine!$B$70 -> 7
A4: Upside | B4: =Engine!$B$101 -> 3116389.5 | C4: =Engine!$B$102 -> 700847.51 | D4: =Engine!$B$103 -> 220847.51 | E4: =Engine!$B$104 -> 58610.169 | F4: =Engine!$B$105 -> 177320.58 | G4: =Engine!$B$106 -> YES | H4: =Engine!$B$107 -> YES | I4: =Engine!$B$108 -> 5
A6: Downside = 50% fewer new customers, 40% lower repeat, +10% supplier cost, +30 collection days. Upside = +40% customers, +30% repeat, -3% supplier cost.

Sheet Sensitivity_Analysis
A1: Stress test | B1: 12-mo revenue | C1: 12-mo op. profit after founder | D1: Delta vs Base profit | E1: Minimum cash | F1: Solvent within NPR 5L? | G1: Solvent without contingency? | H1: First profit month (before founder)
A2: S1 Selling prices -10% | B2: =Engine!$B$139 -> 1785240 | C2: =Engine!$B$141 -> -264235.73 | D2: =C2-Engine!$B$65 -> -186458.4 | E2: =Engine!$B$142 -> -183616.67 | F2: =Engine!$B$144 -> NO | G2: =Engine!$B$145 -> NO | H2: =Engine!$B$146 -> 11
A3: S2 Outsourcing cost +10% | B3: =Engine!$B$177 -> 1983600 | C3: =Engine!$B$179 -> -224013.46 | D3: =C3-Engine!$B$65 -> -146236.13 | E3: =Engine!$B$180 -> -160547.84 | F3: =Engine!$B$182 -> NO | G3: =Engine!$B$183 -> NO | H3: =Engine!$B$184 -> 10
A4: S3 Customer acquisition 50% slower | B4: =Engine!$B$215 -> 991800 | C4: =Engine!$B$217 -> -278888.67 | D4: =C4-Engine!$B$65 -> -201111.33 | E4: =Engine!$B$218 -> -129655.85 | F4: =Engine!$B$220 -> NO | G4: =Engine!$B$221 -> NO | H4: =Engine!$B$222 -> 12
A5: S4 Material cost +15% | B5: =Engine!$B$253 -> 1983600 | C5: =Engine!$B$255 -> -297131.53 | D5: =C5-Engine!$B$65 -> -219354.2 | E5: =Engine!$B$256 -> -233665.91 | F5: =Engine!$B$258 -> NO | G5: =Engine!$B$259 -> NO | H5: =Engine!$B$260 -> none in 12 mo
A6: S5 Customers pay 30 days later | B6: =Engine!$B$291 -> 1983600 | C6: =Engine!$B$293 -> -77777.331 | D6: =C6-Engine!$B$65 -> 0 | E6: =Engine!$B$294 -> -171417.96 | F6: =Engine!$B$296 -> NO | G6: =Engine!$B$297 -> NO | H6: =Engine!$B$298 -> 7
A7: S6 Key supplier fails (months 5-6 sales at 40%, 15k rework) | B7: =Engine!$B$329 -> 1828096.9 | C7: =Engine!$B$331 -> -124309.33 | D7: =C7-Engine!$B$65 -> -46532.003 | E7: =Engine!$B$332 -> -68481.035 | F7: =Engine!$B$334 -> NO | G7: =Engine!$B$335 -> NO | H7: =Engine!$B$336 -> 7
A8: S7 Repeat purchases 50% lower | B8: =Engine!$B$367 -> 1579612.5 | C8: =Engine!$B$369 -> -159695.53 | D8: =C8-Engine!$B$65 -> -81918.194 | E8: =Engine!$B$370 -> -50540.838 | F8: =Engine!$B$372 -> NO | G8: =Engine!$B$373 -> NO | H8: =Engine!$B$374 -> 8
A9: S8 Seasonal concentration (M1-6 at 60%, M7-12 at 140%) | B9: =Engine!$B$405 -> 2426062.5 | C9: =Engine!$B$407 -> 11942.596 | D9: =C9-Engine!$B$65 -> 89719.927 | E9: =Engine!$B$408 -> -43146.073 | F9: =Engine!$B$410 -> NO | G9: =Engine!$B$411 -> NO | H9: =Engine!$B$412 -> 7
A10: S9 Unusable output write-off 25k in M4 + tool repair 20k in M8 | B10: =Engine!$B$443 -> 1983600 | C10: =Engine!$B$445 -> -122777.33 | D10: =C10-Engine!$B$65 -> -45000 | E10: =Engine!$B$446 -> -66949.032 | F10: =Engine!$B$448 -> NO | G10: =Engine!$B$449 -> NO | H10: =Engine!$B$450 -> 7

Sheet Three_Year_Summary
A1: NPR (illustrative, Base) | B1: Year 1 | C1: Year 2 | D1: Year 3
A2: Revenue | B2: =Engine!$B$63 -> 1983600 | C2: =Engine!N46*12*(1+Assumptions!$B$22) -> 4734348.8 | D2: =C2*(1+Assumptions!$B$23) -> 5681218.5
A3: Contribution | B3: =Engine!$B$64 -> 402222.67 | C3: =C2*Break_Even!$B$2 -> 960003.22 | D3: =D2*Break_Even!$B$2 -> 1152003.9
A4: Fixed opex | B4: =Assumptions!$B$29*12 -> 390000 | C4: =B4*(1+Assumptions!$B$24) -> 421200 | D4: =C4*(1+Assumptions!$B$24) -> 454896
A5: Founder compensation | B5: =SUM(Engine!C53:N53) -> 90000 | C5: =Assumptions!$B$12*12*1.3 -> 234000 | D5: =C5*1.1 -> 257400
A6: Operating profit after founder (pre-tax, excl. one-offs) | B6: =B3-B4-B5 -> -77777.331 | C6: =C3-C4-C5 -> 304803.22 | D6: =D3-D4-D5 -> 439707.87
A8: Years 2-3 are extrapolations from LOW-confidence assumptions; treat as illustrative only. Year-1 contribution excludes one-off costs.

Sheet Model_Comparison
A1: Criterion (5 = best/lowest risk) | B1: Weight | C1: A: Design & sourcing agency | D1: B: Hybrid studio | E1: C: In-house workshop | F1: Scoring rationale
A2: Total capital required | B2: 10 | C2: 5 | D2: 3 | E2: 1 | F2: A ~NPR 2.65L set-up; C needs powered machines + stock
A3: Machinery investment | B3: 6 | C3: 5 | D3: 3 | E3: 1 | F3: A none; B one cutter; C several
A4: Available product range | B4: 8 | C4: 5 | D4: 3 | E4: 2 | F4: A can broker any format; C limited to 1-2 formats
A5: Ability to customise | B5: 8 | C5: 3 | D5: 4 | E5: 2 | F5: B controls prototyping/short runs; A depends on suppliers' MOQ
A6: Gross & contribution margin | B6: 8 | C6: 3 | D6: 3 | E6: 3 | F6: A pays supplier margin; C bears wastage/under-utilisation
A7: Minimum viable order volume | B7: 6 | C7: 4 | D7: 3 | E7: 1 | F7: C needs volume to cover fixed cost
A8: Break-even sales | B8: 8 | C8: 4 | D8: 3 | E8: 1 | F8: Lowest fixed cost in A
A9: Working-capital intensity | B9: 7 | C9: 3 | D9: 3 | E9: 2 | F9: Supplier prepayment vs raw-material stock
A10: Production control | B10: 4 | C10: 2 | D10: 4 | E10: 5 | F10: A depends on third parties
A11: Delivery reliability | B11: 6 | C11: 3 | D11: 4 | E11: 2 | F11: Supplier delays hurt A; C lacks capacity/skills
A12: Competition | B12: 5 | C12: 3 | D12: 3 | E12: 2 | F12: C competes head-on with established printers
A13: Customer acquisition difficulty | B13: 5 | C13: 3 | D13: 3 | E13: 3 | F13: Equal; selling is the bottleneck
... A16: Downside risk | B16: 8 | C16: 5 | D16: 3 | E16: 1 | F16: A can stop with little sunk cost
A17: WEIGHTED SCORE (max 5.00) | C17: =SUMPRODUCT($B$2:$B$16,C2:C16)/SUM($B$2:$B$16) -> 3.85 | D17: =SUMPRODUCT($B$2:$B$16,D2:D16)/SUM($B$2:$B$16) -> 3.18 | E17: =SUMPRODUCT($B$2:$B$16,E2:E16)/SUM($B$2:$B$16) -> 1.86
A18: Weights sum | B18: =SUM(B2:B16) -> 100
A19: Scores are analyst judgements informed by the research, not measured data.

Sheet Checks
A1: Check | B1: Result
A2: Recommended budget total equals ceiling (NPR 5,00,000) | B2: =IF(Capital_Allocation!$C$17=Assumptions!$B$2,"OK","ERROR") -> OK
A3: Recommended budget does not exceed ceiling | B3: =IF(Capital_Allocation!$C$17<=Assumptions!$B$2,"OK","ERROR") -> OK
A4: Config A within ceiling | B4: =IF(Capital_Allocation!B17<=Assumptions!$B$2,"OK","ERROR") -> OK
A5: Machinery share of recommended budget (must be < 50%) | B5: =Capital_Allocation!C430/Capital_Allocation!$C$17 -> 0
A6: Working capital + contingency share of recommended budget | B6: =(Capital_Allocation!$C$15+Capital_Allocation!$C$16)/Capital_Allocation!$C$17 -> 0.47
A7: Model-comparison weights sum to 100 | B7: =IF(Model_Comparison!B18=100,"OK","ERROR") -> OK
A8: Base engine: closing cash M12 = opening + cumulative net cash flow | B8: =IF(ABS(Engine!N58-(Capital_Allocation!$C$20+SUM(Engine!C57:N57)))<0.01,"OK","ERROR") -> OK

Sheet Sources_and_Assumptions
A1: ID | B1: Claim | C1: Source | D1: Confidence
A2: E01 | B2: NRB USD selling NPR 155.08; INR (per 100) selling NPR 160.15 on 12 Oct 2026 | C2: https://www.sharesansar.com/newsdetail/nrb-publishes-mondays-forex-rates-us-dollar-fixed-at-rs-15508-2026-10-12 | D2: High
A3: E02 | B3: VAT registration: goods NPR 50 lakh, services/mixed NPR 30 lakh, rate 13%, PAN prerequisite | C3: https://udhamsathi.com/blog/vat-registration-nepal (secondary; cites VAT Act 2052, Finance Act 2081) | D3: Medium
A4: E03 | B4: Box House Nepal retail prices (pastry box 10, 2lb cake box 35, 12in pizza box 20) | C4: https://boxhousenepal.com.np/ | D4: Medium
A5: E04 | B5: Indian cutting plotter / label cutter asking prices | C5: IndiaMART listings via search (see Machinery sheet) | D5: Low
A6: E05 | B6: All supplier costs, selling prices, AOV, funnel, reorder rate, opex | C6: Analyst assumptions - NOT sourced | D6: Low
